Workbook

Sheet Hoy
A1: ¿Qué conviene traer? · 30/10/2026
A2: eBay: vendedor en EE.UU., ≥ 98 % de feedback, nuevo sin open box. Marketplace y Tiendas: el precio más bajo que cuenta en Cochabamba. Costo puesto con el courier más barato, según la hoja Supuestos.
A4: Producto | B4: Tipo | C4: Link del producto | D4: eBay nuevo USD | E4: Envío EE.UU. USD | F4: eBay usado USD | G4: Marketplace Bs | H4: Tiendas Bs | I4: Dólar BCB | J4: Dólar paralelo | K4: Peso g | L4: Courier /u USD | M4: Costo puesto Bs | N4: Mejor local Bs | O4: Ganancia /u Bs | P4: Margen | Q4: Estado
A5: SSD NVMe 2TB | B5: SSD | C5: ver en eBay | D5: 185 | E5: 0 | F5: 154.99 | G5: 3100 | H5: 4060 | I5: =INDEX(Dólar!$B:$B,MATCH(MAX(Dólar!$A:$A),Dólar!$A:$A,0)) | J5: =INDEX(Dólar!$E:$E,MATCH(MAX(Dólar!$A:$A),Dólar!$A:$A,0)) | K5: 80 | L5: =IF(D5="","",MIN(MAX(Supuestos!$B$5,CEILING((K5*Supuestos!$B$3+Supuestos!$B$7)/1000,Supuestos!$B$6))*Supuestos!$B$4/Supuestos!$B$3,Supuestos!$B$8+D5*Supuestos!$B$9)) | M5: =IF(D5="","",(D5+E5+L5+(D5+E5)*Supuestos!$B$10)*Supuestos!$B$11) | N5: =IF(COUNT(G5:H5)=0,"",MIN(G5:H5)) | O5: =IF(OR(M5="",N5=""),"",N5-M5) | P5: =IF(O5="","",O5/N5) | Q5: =IF(P5="",IF(AND(D5="",N5=""),"Sin datos",IF(D5="","Sin precio eBay","Sin precio local")),IF(P5>=Supuestos!$B$12,"Conviene",IF(P5>=Supuestos!$B$13,"Justo","No conviene")))
A6: Intel Core Ultra 7 265K | B6: CPU | C6: ver en eBay | D6: 248 | E6: 0 | F6: 249.99 | H6: 3950 | I6: =INDEX(Dólar!$B:$B,MATCH(MAX(Dólar!$A:$A),Dólar!$A:$A,0)) | J6: =INDEX(Dólar!$E:$E,MATCH(MAX(Dólar!$A:$A),Dólar!$A:$A,0)) | K6: 300 | L6: =IF(D6="","",MIN(MAX(Supuestos!$B$5,CEILING((K6*Supuestos!$B$3+Supuestos!$B$7)/1000,Supuestos!$B$6))*Supuestos!$B$4/Supuestos!$B$3,Supuestos!$B$8+D6*Supuestos!$B$9)) | M6: =IF(D6="","",(D6+E6+L6+(D6+E6)*Supuestos!$B$10)*Supuestos!$B$11) | N6: =IF(COUNT(G6:H6)=0,"",MIN(G6:H6)) | O6: =IF(OR(M6="",N6=""),"",N6-M6) | P6: =IF(O6="","",O6/N6) | Q6: =IF(P6="",IF(AND(D6="",N6=""),"Sin datos",IF(D6="","Sin precio eBay","Sin precio local")),IF(P6>=Supuestos!$B$12,"Conviene",IF(P6>=Supuestos!$B$13,"Justo","No conviene")))
A7: Intel Core i5-12400F | B7: CPU | C7: ver en eBay | D7: 140 | E7: 0 | F7: 119.99 | G7: 2350 | H7: 2260 | I7: =INDEX(Dólar!$B:$B,MATCH(MAX(Dólar!$A:$A),Dólar!$A:$A,0)) | J7: =INDEX(Dólar!$E:$E,MATCH(MAX(Dólar!$A:$A),Dólar!$A:$A,0)) | K7: 250 | L7: =IF(D7="","",MIN(MAX(Supuestos!$B$5,CEILING((K7*Supuestos!$B$3+Supuestos!$B$7)/1000,Supuestos!$B$6))*Supuestos!$B$4/Supuestos!$B$3,Supuestos!$B$8+D7*Supuestos!$B$9)) | M7: =IF(D7="","",(D7+E7+L7+(D7+E7)*Supuestos!$B$10)*Supuestos!$B$11) | N7: =IF(COUNT(G7:H7)=0,"",MIN(G7:H7)) | O7: =IF(OR(M7="",N7=""),"",N7-M7) | P7: =IF(O7="","",O7/N7) | Q7: =IF(P7="",IF(AND(D7="",N7=""),"Sin datos",IF(D7="","Sin precio eBay","Sin precio local")),IF(P7>=Supuestos!$B$12,"Conviene",IF(P7>=Supuestos!$B$13,"Justo","No conviene")))
A8: Ryzen 7 7800X3D | B8: CPU | C8: ver en eBay | D8: 329 | E8: 0 | F8: 265 | G8: 4800 | H8: 4760 | I8: =INDEX(Dólar!$B:$B,MATCH(MAX(Dólar!$A:$A),Dólar!$A:$A,0)) | J8: =INDEX(Dólar!$E:$E,MATCH(MAX(Dólar!$A:$A),Dólar!$A:$A,0)) | K8: 350 | L8: =IF(D8="","",MIN(MAX(Supuestos!$B$5,CEILING((K8*Supuestos!$B$3+Supuestos!$B$7)/1000,Supuestos!$B$6))*Supuestos!$B$4/Supuestos!$B$3,Supuestos!$B$8+D8*Supuestos!$B$9)) | M8: =IF(D8="","",(D8+E8+L8+(D8+E8)*Supuestos!$B$10)*Supuestos!$B$11) | N8: =IF(COUNT(G8:H8)=0,"",MIN(G8:H8)) | O8: =IF(OR(M8="",N8=""),"",N8-M8) | P8: =IF(O8="","",O8/N8) | Q8: =IF(P8="",IF(AND(D8="",N8=""),"Sin datos",IF(D8="","Sin precio eBay","Sin precio local")),IF(P8>=Supuestos!$B$12,"Conviene",IF(P8>=Supuestos!$B$13,"Justo","No conviene")))
A9: Intel Core i5-14400F | B9: CPU | C9: ver en eBay | D9: 164.49 | E9: 0 | F9: 130 | H9: 2384 | I9: =INDEX(Dólar!$B:$B,MATCH(MAX(Dólar!$A:$A),Dólar!$A:$A,0)) | J9: =INDEX(Dólar!$E:$E,MATCH(MAX(Dólar!$A:$A),Dólar!$A:$A,0)) | K9: 250 | L9: =IF(D9="","",MIN(MAX(Supuestos!$B$5,CEILING((K9*Supuestos!$B$3+Supuestos!$B$7)/1000,Supuestos!$B$6))*Supuestos!$B$4/Supuestos!$B$3,Supuestos!$B$8+D9*Supuestos!$B$9)) | M9: =IF(D9="","",(D9+E9+L9+(D9+E9)*Supuestos!$B$10)*Supuestos!$B$11) | N9: =IF(COUNT(G9:H9)=0,"",MIN(G9:H9)) | O9: =IF(OR(M9="",N9=""),"",N9-M9) | P9: =IF(O9="","",O9/N9) | Q9: =IF(P9="",IF(AND(D9="",N9=""),"Sin datos",IF(D9="","Sin precio eBay","Sin precio local")),IF(P9>=Supuestos!$B$12,"Conviene",IF(P9>=Supuestos!$B$13,"Justo","No conviene")))
A10: Ryzen 5 7600 | B10: CPU | C10: ver en eBay | D10: 199.99 | E10: 0 | F10: 114.99 | H10: 2800 | I10: =INDEX(Dólar!$B:$B,MATCH(MAX(Dólar!$A:$A),Dólar!$A:$A,0)) | J10: =INDEX(Dólar!$E:$E,MATCH(MAX(Dólar!$A:$A),Dólar!$A:$A,0)) | K10: 350 | L10: =IF(D10="","",MIN(MAX(Supuestos!$B$5,CEILING((K10*Supuestos!$B$3+Supuestos!$B$7)/1000,Supuestos!$B$6))*Supuestos!$B$4/Supuestos!$B$3,Supuestos!$B$8+D10*Supuestos!$B$9)) | M10: =IF(D10="","",(D10+E10+L10+(D10+E10)*Supuestos!$B$10)*Supuestos!$B$11) | N10: =IF(COUNT(G10:H10)=0,"",MIN(G10:H10)) | O10: =IF(OR(M10="",N10=""),"",N10-M10) | P10: =IF(O10="","",O10/N10) | Q10: =IF(P10="",IF(AND(D10="",N10=""),"Sin datos",IF(D10="","Sin precio eBay","Sin precio local")),IF(P10>=Supuestos!$B$12,"Conviene",IF(P10>=Supuestos!$B$13,"Justo","No conviene")))
A11: Ryzen 7 7700X | B11: CPU | C11: ver en eBay | D11: 199 | E11: 20 | F11: 189.99 | G11: 3000 | H11: 3480 | I11: =INDEX(Dólar!$B:$B,MATCH(MAX(Dólar!$A:$A),Dólar!$A:$A,0)) | J11: =INDEX(Dólar!$E:$E,MATCH(MAX(Dólar!$A:$A),Dólar!$A:$A,0)) | K11: 350 | L11: =IF(D11="","",MIN(MAX(Supuestos!$B$5,CEILING((K11*Supuestos!$B$3+Supuestos!$B$7)/1000,Supuestos!$B$6))*Supuestos!$B$4/Supuestos!$B$3,Supuestos!$B$8+D11*Supuestos!$B$9)) | M11: =IF(D11="","",(D11+E11+L11+(D11+E11)*Supuestos!$B$10)*Supuestos!$B$11) | N11: =IF(COUNT(G11:H11)=0,"",MIN(G11:H11)) | O11: =IF(OR(M11="",N11=""),"",N11-M11) | P11: =IF(O11="","",O11/N11) | Q11: =IF(P11="",IF(AND(D11="",N11=""),"Sin datos",IF(D11="","Sin precio eBay","Sin precio local")),IF(P11>=Supuestos!$B$12,"Conviene",IF(P11>=Supuestos!$B$13,"Justo","No conviene")))
A12: Corsair Vengeance RGB DDR5 32GB (2x16) 6000 | B12: RAM | C12: ver en eBay | D12: 450 | E12: 0 | F12: 419.99 | G12: 5800 | I12: =INDEX(Dólar!$B:$B,MATCH(MAX(Dólar!$A:$A),Dólar!$A:$A,0)) | J12: =INDEX(Dólar!$E:$E,MATCH(MAX(Dólar!$A:$A),Dólar!$A:$A,0)) | K12: 150 | L12: =IF(D12="","",MIN(MAX(Supuestos!$B$5,CEILING((K12*Supuestos!$B$3+Supuestos!$B$7)/1000,Supuestos!$B$6))*Supuestos!$B$4/Supuestos!$B$3,Supuestos!$B$8+D12*Supuestos!$B$9)) | M12: =IF(D12="","",(D12+E12+L12+(D12+E12)*Supuestos!$B$10)*Supuestos!$B$11) | N12: =IF(COUNT(G12:H12)=0,"",MIN(G12:H12)) | O12: =IF(OR(M12="",N12=""),"",N12-M12) | P12: =IF(O12="","",O12/N12) | Q12: =IF(P12="",IF(AND(D12="",N12=""),"Sin datos",IF(D12="","Sin precio eBay","Sin precio local")),IF(P12>=Supuestos!$B$12,"Conviene",IF(P12>=Supuestos!$B$13,"Justo","No conviene")))
A13: Ryzen 9 9950X | B13: CPU | C13: ver en eBay | D13: 549.99 | E13: 0 | F13: 454.99 | H13: 5580 | I13: =INDEX(Dólar!$B:$B,MATCH(MAX(Dólar!$A:$A),Dólar!$A:$A,0)) | J13: =INDEX(Dólar!$E:$E,MATCH(MAX(Dólar!$A:$A),Dólar!$A:$A,0)) | K13: 350 | L13: =IF(D13="","",MIN(MAX(Supuestos!$B$5,CEILING((K13*Supuestos!$B$3+Supuestos!$B$7)/1000,Supuestos!$B$6))*Supuestos!$B$4/Supuestos!$B$3,Supuestos!$B$8+D13*Supuestos!$B$9)) | M13: =IF(D13="","",(D13+E13+L13+(D13+E13)*Supuestos!$B$10)*Supuestos!$B$11) | N13: =IF(COUNT(G13:H13)=0,"",MIN(G13:H13)) | O13: =IF(OR(M13="",N13=""),"",N13-M13) | P13: =IF(O13="","",O13/N13) | Q13: =IF(P13="",IF(AND(D13="",N13=""),"Sin datos",IF(D13="","Sin precio eBay","Sin precio local")),IF(P13>=Supuestos!$B$12,"Conviene",IF(P13>=Supuestos!$B$13,"Justo","No conviene")))
A14: Corsair Vengeance RGB DDR5 32GB (2x16) 5600 | B14: RAM | C14: ver en eBay | D14: 459 | E14: 0 | F14: 389.99 | G14: 4500 | I14: =INDEX(Dólar!$B:$B,MATCH(MAX(Dólar!$A:$A),Dólar!$A:$A,0)) | J14: =INDEX(Dólar!$E:$E,MATCH(MAX(Dólar!$A:$A),Dólar!$A:$A,0)) | K14: 150 | L14: =IF(D14="","",MIN(MAX(Supuestos!$B$5,CEILING((K14*Supuestos!$B$3+Supuestos!$B$7)/1000,Supuestos!$B$6))*Supuestos!$B$4/Supuestos!$B$3,Supuestos!$B$8+D14*Supuestos!$B$9)) | M14: =IF(D14="","",(D14+E14+L14+(D14+E14)*Supuestos!$B$10)*Supuestos!$B$11) | N14: =IF(COUNT(G14:H14)=0,"",MIN(G14:H14)) | O14: =IF(OR(M14="",N14=""),"",N14-M14) | P14: =IF(O14="","",O14/N14) | Q14: =IF(P14="",IF(AND(D14="",N14=""),"Sin datos",IF(D14="","Sin precio eBay","Sin precio local")),IF(P14>=Supuestos!$B$12,"Conviene",IF(P14>=Supuestos!$B$13,"Justo","No conviene")))
A15: Intel Core i5-13400 | B15: CPU | C15: ver en eBay | D15: 259.78 | E15: 0 | F15: 129.99 | H15: 2300 | I15: =INDEX(Dólar!$B:$B,MATCH(MAX(Dólar!$A:$A),Dólar!$A:$A,0)) | J15: =INDEX(Dólar!$E:$E,MATCH(MAX(Dólar!$A:$A),Dólar!$A:$A,0)) | K15: 300 | L15: =IF(D15="","",MIN(MAX(Supuestos!$B$5,CEILING((K15*Supuestos!$B$3+Supuestos!$B$7)/1000,Supuestos!$B$6))*Supuestos!$B$4/Supuestos!$B$3,Supuestos!$B$8+D15*Supuestos!$B$9)) | M15: =IF(D15="","",(D15+E15+L15+(D15+E15)*Supuestos!$B$10)*Supuestos!$B$11) | N15: =IF(COUNT(G15:H15)=0,"",MIN(G15:H15)) | O15: =IF(OR(M15="",N15=""),"",N15-M15) | P15: =IF(O15="","",O15/N15) | Q15: =IF(P15="",IF(AND(D15="",N15=""),"Sin datos",IF(D15="","Sin precio eBay","Sin precio local")),IF(P15>=Supuestos!$B$12,"Conviene",IF(P15>=Supuestos!$B$13,"Justo","No conviene")))
A16: SSD NVMe 1TB | B16: SSD | C16: ver en eBay | D16: 119.99 | E16: 0 | F16: 99 | G16: 1100 | H16: 1754 | I16: =INDEX(Dólar!$B:$B,MATCH(MAX(Dólar!$A:$A),Dólar!$A:$A,0)) | J16: =INDEX(Dólar!$E:$E,MATCH(MAX(Dólar!$A:$A),Dólar!$A:$A,0)) | K16: 80 | L16: =IF(D16="","",MIN(MAX(Supuestos!$B$5,CEILING((K16*Supuestos!$B$3+Supuestos!$B$7)/1000,Supuestos!$B$6))*Supuestos!$B$4/Supuestos!$B$3,Supuestos!$B$8+D16*Supuestos!$B$9)) | M16: =IF(D16="","",(D16+E16+L16+(D16+E16)*Supuestos!$B$10)*Supuestos!$B$11) | N16: =IF(COUNT(G16:H16)=0,"",MIN(G16:H16)) | O16: =IF(OR(M16="",N16=""),"",N16-M16) | P16: =IF(O16="","",O16/N16) | Q16: =IF(P16="",IF(AND(D16="",N16=""),"Sin datos",IF(D16="","Sin precio eBay","Sin precio local")),IF(P16>=Supuestos!$B$12,"Conviene",IF(P16>=Supuestos!$B$13,"Justo","No conviene")))
A17: RAM DDR4 16GB (2x8) 3200 | B17: RAM | C17: ver en eBay | D17: 75 | E17: 0 | F17: 59.99 | G17: 540 | H17: 2150 | I17: =INDEX(Dólar!$B:$B,MATCH(MAX(Dólar!$A:$A),Dólar!$A:$A,0)) | J17: =INDEX(Dólar!$E:$E,MATCH(MAX(Dólar!$A:$A),Dólar!$A:$A,0)) | K17: 120 | L17: =IF(D17="","",MIN(MAX(Supuestos!$B$5,CEILING((K17*Supuestos!$B$3+Supuestos!$B$7)/1000,Supuestos!$B$6))*Supuestos!$B$4/Supuestos!$B$3,Supuestos!$B$8+D17*Supuestos!$B$9)) | M17: =IF(D17="","",(D17+E17+L17+(D17+E17)*Supuestos!$B$10)*Supuestos!$B$11) | N17: =IF(COUNT(G17:H17)=0,"",MIN(G17:H17)) | O17: =IF(OR(M17="",N17=""),"",N17-M17) | P17: =IF(O17="","",O17/N17) | Q17: =IF(P17="",IF(AND(D17="",N17=""),"Sin datos",IF(D17="","Sin precio eBay","Sin precio local")),IF(P17>=Supuestos!$B$12,"Conviene",IF(P17>=Supuestos!$B$13,"Justo","No conviene")))
A18: Ryzen 5 5600 | B18: CPU | C18: ver en eBay | D18: 138.9 | E18: 0 | F18: 131.99 | I18: =INDEX(Dólar!$B:$B,MATCH(MAX(Dólar!$A:$A),Dólar!$A:$A,0)) | J18: =INDEX(Dólar!$E:$E,MATCH(MAX(Dólar!$A:$A),Dólar!$A:$A,0)) | K18: 350 | L18: =IF(D18="","",MIN(MAX(Supuestos!$B$5,CEILING((K18*Supuestos!$B$3+Supuestos!$B$7)/1000,Supuestos!$B$6))*Supuestos!$B$4/Supuestos!$B$3,Supuestos!$B$8+D18*Supuestos!$B$9)) | M18: =IF(D18="","",(D18+E18+L18+(D18+E18)*Supuestos!$B$10)*Supuestos!$B$11) | N18: =IF(COUNT(G18:H18)=0,"",MIN(G18:H18)) | O18: =IF(OR(M18="",N18=""),"",N18-M18) | P18: =IF(O18="","",O18/N18) | Q18: =IF(P18="",IF(AND(D18="",N18=""),"Sin datos",IF(D18="","Sin precio eBay","Sin precio local")),IF(P18>=Supuestos!$B$12,"Conviene",IF(P18>=Supuestos!$B$13,"Justo","No conviene")))
A19: Ryzen 7 5700X3D | B19: CPU | C19: ver en eBay | F19: 336 | I19: =INDEX(Dólar!$B:$B,MATCH(MAX(Dólar!$A:$A),Dólar!$A:$A,0)) | J19: =INDEX(Dólar!$E:$E,MATCH(MAX(Dólar!$A:$A),Dólar!$A:$A,0)) | K19: 350 | L19: =IF(D19="","",MIN(MAX(Supuestos!$B$5,CEILING((K19*Supuestos!$B$3+Supuestos!$B$7)/1000,Supuestos!$B$6))*Supuestos!$B$4/Supuestos!$B$3,Supuestos!$B$8+D19*Supuestos!$B$9)) | M19: =IF(D19="","",(D19+E19+L19+(D19+E19)*Supuestos!$B$10)*Supuestos!$B$11) | N19: =IF(COUNT(G19:H19)=0,"",MIN(G19:H19)) | O19: =IF(OR(M19="",N19=""),"",N19-M19) | P19: =IF(O19="","",O19/N19) | Q19: =IF(P19="",IF(AND(D19="",N19=""),"Sin datos",IF(D19="","Sin precio eBay","Sin precio local")),IF(P19>=Supuestos!$B$12,"Conviene",IF(P19>=Supuestos!$B$13,"Justo","No conviene")))
A20: Ryzen 5 7500F | B20: CPU | C20: ver en eBay | D20: 135.6 | E20: 0 | F20: 114.99 | I20: =INDEX(Dólar!$B:$B,MATCH(MAX(Dólar!$A:$A),Dólar!$A:$A,0)) | J20: =INDEX(Dólar!$E:$E,MATCH(MAX(Dólar!$A:$A),Dólar!$A:$A,0)) | K20: 350 | L20: =IF(D20="","",MIN(MAX(Supuestos!$B$5,CEILING((K20*Supuestos!$B$3+Supuestos!$B$7)/1000,Supuestos!$B$6))*Supuestos!$B$4/Supuestos!$B$3,Supuestos!$B$8+D20*Supuestos!$B$9)) | M20: =IF(D20="","",(D20+E20+L20+(D20+E20)*Supuestos!$B$10)*Supuestos!$B$11) | N20: =IF(COUNT(G20:H20)=0,"",MIN(G20:H20)) | O20: =IF(OR(M20="",N20=""),"",N20-M20) | P20: =IF(O20="","",O20/N20) | Q20: =IF(P20="",IF(AND(D20="",N20=""),"Sin datos",IF(D20="","Sin precio eBay","Sin precio local")),IF(P20>=Supuestos!$B$12,"Conviene",IF(P20>=Supuestos!$B$13,"Justo","No conviene")))
A22: Azul: datos de eBay, Marketplace y tiendas (de los CSV del repo). Negro: fórmulas. Para probar otros supuestos (unidades, aduana, dólar) cambia la hoja Supuestos.

Sheet Historial
A1: Fecha | B1: Producto | C1: Tipo | D1: eBay nuevo USD | E1: eBay usado USD | F1: Marketplace Bs | G1: Tiendas Bs | H1: Dólar BCB | I1: Dólar paralelo | J1: Link del producto | K1: Fecha anterior | L1: Δ eBay nuevo | M1: Δ eBay usado | N1: Δ Marketplace | O1: Δ Tiendas
A2: 46325 | B2: SSD NVMe 2TB | C2: SSD | D2: 185 | F2: 3100 | H2: =IFERROR(IF(INDEX(Dólar!$B:$B,MATCH(A2,Dólar!$A:$A,0))="","",INDEX(Dólar!$B:$B,MATCH(A2,Dólar!$A:$A,0))),"") | I2: =IFERROR(INDEX(Dólar!$E:$E,MATCH(A2,Dólar!$A:$A,0)),"") | J2: ver anuncio | K2: 46324 | L2: =IF(OR($K2="",D2=""),"",IF(COUNTIFS($B:$B,$B2,$A:$A,$K2,D:D,">=0")=0,"",D2-SUMIFS(D:D,$B:$B,$B2,$A:$A,$K2))) | M2: =IF(OR($K2="",E2=""),"",IF(COUNTIFS($B:$B,$B2,$A:$A,$K2,E:E,">=0")=0,"",E2-SUMIFS(E:E,$B:$B,$B2,$A:$A,$K2))) | N2: =IF(OR($K2="",F2=""),"",IF(COUNTIFS($B:$B,$B2,$A:$A,$K2,F:F,">=0")=0,"",F2-SUMIFS(F:F,$B:$B,$B2,$A:$A,$K2))) | O2: =IF(OR($K2="",G2=""),"",IF(COUNTIFS($B:$B,$B2,$A:$A,$K2,G:G,">=0")=0,"",G2-SUMIFS(G:G,$B:$B,$B2,$A:$A,$K2)))
A3: 46325 | B3: SSD NVMe 1TB | C3: SSD | D3: 119.99 | F3: 1675 | H3: =IFERROR(IF(INDEX(Dólar!$B:$B,MATCH(A3,Dólar!$A:$A,0))="","",INDEX(Dólar!$B:$B,MATCH(A3,Dólar!$A:$A,0))),"") | I3: =IFERROR(INDEX(Dólar!$E:$E,MATCH(A3,Dólar!$A:$A,0)),"") | J3: ver anuncio | K3: 46324 | L3: =IF(OR($K3="",D3=""),"",IF(COUNTIFS($B:$B,$B3,$A:$A,$K3,D:D,">=0")=0,"",D3-SUMIFS(D:D,$B:$B,$B3,$A:$A,$K3))) | M3: =IF(OR($K3="",E3=""),"",IF(COUNTIFS($B:$B,$B3,$A:$A,$K3,E:E,">=0")=0,"",E3-SUMIFS(E:E,$B:$B,$B3,$A:$A,$K3))) | N3: =IF(OR($K3="",F3=""),"",IF(COUNTIFS($B:$B,$B3,$A:$A,$K3,F:F,">=0")=0,"",F3-SUMIFS(F:F,$B:$B,$B3,$A:$A,$K3))) | O3: =IF(OR($K3="",G3=""),"",IF(COUNTIFS($B:$B,$B3,$A:$A,$K3,G:G,">=0")=0,"",G3-SUMIFS(G:G,$B:$B,$B3,$A:$A,$K3)))
A4: 46325 | B4: Ryzen 9 9950X | C4: CPU | D4: 549.99 | H4: =IFERROR(IF(INDEX(Dólar!$B:$B,MATCH(A4,Dólar!$A:$A,0))="","",INDEX(Dólar!$B:$B,MATCH(A4,Dólar!$A:$A,0))),"") | I4: =IFERROR(INDEX(Dólar!$E:$E,MATCH(A4,Dólar!$A:$A,0)),"") | J4: ver anuncio | K4: 46324 | L4: =IF(OR($K4="",D4=""),"",IF(COUNTIFS($B:$B,$B4,$A:$A,$K4,D:D,">=0")=0,"",D4-SUMIFS(D:D,$B:$B,$B4,$A:$A,$K4))) | M4: =IF(OR($K4="",E4=""),"",IF(COUNTIFS($B:$B,$B4,$A:$A,$K4,E:E,">=0")=0,"",E4-SUMIFS(E:E,$B:$B,$B4,$A:$A,$K4))) | N4: =IF(OR($K4="",F4=""),"",IF(COUNTIFS($B:$B,$B4,$A:$A,$K4,F:F,">=0")=0,"",F4-SUMIFS(F:F,$B:$B,$B4,$A:$A,$K4))) | O4: =IF(OR($K4="",G4=""),"",IF(COUNTIFS($B:$B,$B4,$A:$A,$K4,G:G,">=0")=0,"",G4-SUMIFS(G:G,$B:$B,$B4,$A:$A,$K4)))
A5: 46325 | B5: Ryzen 7 7800X3D | C5: CPU | D5: 329 | F5: 5190 | H5: =IFERROR(IF(INDEX(Dólar!$B:$B,MATCH(A5,Dólar!$A:$A,0))="","",INDEX(Dólar!$B:$B,MATCH(A5,Dólar!$A:$A,0))),"") | I5: =IFERROR(INDEX(Dólar!$E:$E,MATCH(A5,Dólar!$A:$A,0)),"") | J5: ver anuncio | K5: 46324 | L5: =IF(OR($K5="",D5=""),"",IF(COUNTIFS($B:$B,$B5,$A:$A,$K5,D:D,">=0")=0,"",D5-SUMIFS(D:D,$B:$B,$B5,$A:$A,$K5))) | M5: =IF(OR($K5="",E5=""),"",IF(COUNTIFS($B:$B,$B5,$A:$A,$K5,E:E,">=0")=0,"",E5-SUMIFS(E:E,$B:$B,$B5,$A:$A,$K5))) | N5: =IF(OR($K5="",F5=""),"",IF(COUNTIFS($B:$B,$B5,$A:$A,$K5,F:F,">=0")=0,"",F5-SUMIFS(F:F,$B:$B,$B5,$A:$A,$K5))) | O5: =IF(OR($K5="",G5=""),"",IF(COUNTIFS($B:$B,$B5,$A:$A,$K5,G:G,">=0")=0,"",G5-SUMIFS(G:G,$B:$B,$B5,$A:$A,$K5)))
A6: 46325 | B6: Ryzen 7 7700X | C6: CPU | D6: 219 | F6: 3000 | H6: =IFERROR(IF(INDEX(Dólar!$B:$B,MATCH(A6,Dólar!$A:$A,0))="","",INDEX(Dólar!$B:$B,MATCH(A6,Dólar!$A:$A,0))),"") | I6: =IFERROR(INDEX(Dólar!$E:$E,MATCH(A6,Dólar!$A:$A,0)),"") | J6: ver anuncio | K6: 46324 | L6: =IF(OR($K6="",D6=""),"",IF(COUNTIFS($B:$B,$B6,$A:$A,$K6,D:D,">=0")=0,"",D6-SUMIFS(D:D,$B:$B,$B6,$A:$A,$K6))) | M6: =IF(OR($K6="",E6=""),"",IF(COUNTIFS($B:$B,$B6,$A:$A,$K6,E:E,">=0")=0,"",E6-SUMIFS(E:E,$B:$B,$B6,$A:$A,$K6))) | N6: =IF(OR($K6="",F6=""),"",IF(COUNTIFS($B:$B,$B6,$A:$A,$K6,F:F,">=0")=0,"",F6-SUMIFS(F:F,$B:$B,$B6,$A:$A,$K6))) | O6: =IF(OR($K6="",G6=""),"",IF(COUNTIFS($B:$B,$B6,$A:$A,$K6,G:G,">=0")=0,"",G6-SUMIFS(G:G,$B:$B,$B6,$A:$A,$K6)))
A7: 46325 | B7: Ryzen 5 7600 | C7: CPU | D7: 199.99 | H7: =IFERROR(IF(INDEX(Dólar!$B:$B,MATCH(A7,Dólar!$A:$A,0))="","",INDEX(Dólar!$B:$B,MATCH(A7,Dólar!$A:$A,0))),"") | I7: =IFERROR(INDEX(Dólar!$E:$E,MATCH(A7,Dólar!$A:$A,0)),"") | J7: ver anuncio | K7: 46324 | L7: =IF(OR($K7="",D7=""),"",IF(COUNTIFS($B:$B,$B7,$A:$A,$K7,D:D,">=0")=0,"",D7-SUMIFS(D:D,$B:$B,$B7,$A:$A,$K7))) | M7: =IF(OR($K7="",E7=""),"",IF(COUNTIFS($B:$B,$B7,$A:$A,$K7,E:E,">=0")=0,"",E7-SUMIFS(E:E,$B:$B,$B7,$A:$A,$K7))) | N7: =IF(OR($K7="",F7=""),"",IF(COUNTIFS($B:$B,$B7,$A:$A,$K7,F:F,">=0")=0,"",F7-SUMIFS(F:F,$B:$B,$B7,$A:$A,$K7))) | O7: =IF(OR($K7="",G7=""),"",IF(COUNTIFS($B:$B,$B7,$A:$A,$K7,G:G,">=0")=0,"",G7-SUMIFS(G:G,$B:$B,$B7,$A:$A,$K7)))
A8: 46325 | B8: Ryzen 5 7500F | C8: CPU | D8: 135.6 | H8: =IFERROR(IF(INDEX(Dólar!$B:$B,MATCH(A8,Dólar!$A:$A,0))="","",INDEX(Dólar!$B:$B,MATCH(A8,Dólar!$A:$A,0))),"") | I8: =IFERROR(INDEX(Dólar!$E:$E,MATCH(A8,Dólar!$A:$A,0)),"") | J8: ver anuncio | K8: 46324 | L8: =IF(OR($K8="",D8=""),"",IF(COUNTIFS($B:$B,$B8,$A:$A,$K8,D:D,">=0")=0,"",D8-SUMIFS(D:D,$B:$B,$B8,$A:$A,$K8))) | M8: =IF(OR($K8="",E8=""),"",IF(COUNTIFS($B:$B,$B8,$A:$A,$K8,E:E,">=0")=0,"",E8-SUMIFS(E:E,$B:$B,$B8,$A:$A,$K8))) | N8: =IF(OR($K8="",F8=""),"",IF(COUNTIFS($B:$B,$B8,$A:$A,$K8,F:F,">=0")=0,"",F8-SUMIFS(F:F,$B:$B,$B8,$A:$A,$K8))) | O8: =IF(OR($K8="",G8=""),"",IF(COUNTIFS($B:$B,$B8,$A:$A,$K8,G:G,">=0")=0,"",G8-SUMIFS(G:G,$B:$B,$B8,$A:$A,$K8)))
A9: 46325 | B9: Ryzen 5 5600 | C9: CPU | D9: 138.9 | H9: =IFERROR(IF(INDEX(Dólar!$B:$B,MATCH(A9,Dólar!$A:$A,0))="","",INDEX(Dólar!$B:$B,MATCH(A9,Dólar!$A:$A,0))),"") | I9: =IFERROR(INDEX(Dólar!$E:$E,MATCH(A9,Dólar!$A:$A,0)),"") | J9: ver anuncio | K9: 46324 | L9: =IF(OR($K9="",D9=""),"",IF(COUNTIFS($B:$B,$B9,$A:$A,$K9,D:D,">=0")=0,"",D9-SUMIFS(D:D,$B:$B,$B9,$A:$A,$K9))) | M9: =IF(OR($K9="",E9=""),"",IF(COUNTIFS($B:$B,$B9,$A:$A,$K9,E:E,">=0")=0,"",E9-SUMIFS(E:E,$B:$B,$B9,$A:$A,$K9))) | N9: =IF(OR($K9="",F9=""),"",IF(COUNTIFS($B:$B,$B9,$A:$A,$K9,F:F,">=0")=0,"",F9-SUMIFS(F:F,$B:$B,$B9,$A:$A,$K9))) | O9: =IF(OR($K9="",G9=""),"",IF(COUNTIFS($B:$B,$B9,$A:$A,$K9,G:G,">=0")=0,"",G9-SUMIFS(G:G,$B:$B,$B9,$A:$A,$K9)))
A10: 46325 | B10: RAM DDR4 16GB (2x8) 3200 | C10: RAM | D10: 75 | H10: =IFERROR(IF(INDEX(Dólar!$B:$B,MATCH(A10,Dólar!$A:$A,0))="","",INDEX(Dólar!$B:$B,MATCH(A10,Dólar!$A:$A,0))),"") | I10: =IFERROR(INDEX(Dólar!$E:$E,MATCH(A10,Dólar!$A:$A,0)),"") | J10: ver anuncio | K10: 46324 | L10: =IF(OR($K10="",D10=""),"",IF(COUNTIFS($B:$B,$B10,$A:$A,$K10,D:D,">=0")=0,"",D10-SUMIFS(D:D,$B:$B,$B10,$A:$A,$K10))) | M10: =IF(OR($K10="",E10=""),"",IF(COUNTIFS($B:$B,$B10,$A:$A,$K10,E:E,">=0")=0,"",E10-SUMIFS(E:E,$B:$B,$B10,$A:$A,$K10))) | N10: =IF(OR($K10="",F10=""),"",IF(COUNTIFS($B:$B,$B10,$A:$A,$K10,F:F,">=0")=0,"",F10-SUMIFS(F:F,$B:$B,$B10,$A:$A,$K10))) | O10: =IF(OR($K10="",G10=""),"",IF(COUNTIFS($B:$B,$B10,$A:$A,$K10,G:G,">=0")=0,"",G10-SUMIFS(G:G,$B:$B,$B10,$A:$A,$K10)))
A11: 46325 | B11: Intel Core i5-14400F | C11: CPU | D11: 164.49 | H11: =IFERROR(IF(INDEX(Dólar!$B:$B,MATCH(A11,Dólar!$A:$A,0))="","",INDEX(Dólar!$B:$B,MATCH(A11,Dólar!$A:$A,0))),"") | I11: =IFERROR(INDEX(Dólar!$E:$E,MATCH(A11,Dólar!$A:$A,0)),"") | J11: ver anuncio | K11: 46324 | L11: =IF(OR($K11="",D11=""),"",IF(COUNTIFS($B:$B,$B11,$A:$A,$K11,D:D,">=0")=0,"",D11-SUMIFS(D:D,$B:$B,$B11,$A:$A,$K11))) | M11: =IF(OR($K11="",E11=""),"",IF(COUNTIFS($B:$B,$B11,$A:$A,$K11,E:E,">=0")=0,"",E11-SUMIFS(E:E,$B:$B,$B11,$A:$A,$K11))) | N11: =IF(OR($K11="",F11=""),"",IF(COUNTIFS($B:$B,$B11,$A:$A,$K11,F:F,">=0")=0,"",F11-SUMIFS(F:F,$B:$B,$B11,$A:$A,$K11))) | O11: =IF(OR($K11="",G11=""),"",IF(COUNTIFS($B:$B,$B11,$A:$A,$K11,G:G,">=0")=0,"",G11-SUMIFS(G:G,$B:$B,$B11,$A:$A,$K11)))
A12: 46325 | B12: Intel Core i5-13400 | C12: CPU | H12: =IFERROR(IF(INDEX(Dólar!$B:$B,MATCH(A12,Dólar!$A:$A,0))="","",INDEX(Dólar!$B:$B,MATCH(A12,Dólar!$A:$A,0))),"") | I12: =IFERROR(INDEX(Dólar!$E:$E,MATCH(A12,Dólar!$A:$A,0)),"") | K12: 46324 | L12: =IF(OR($K12="",D12=""),"",IF(COUNTIFS($B:$B,$B12,$A:$A,$K12,D:D,">=0")=0,"",D12-SUMIFS(D:D,$B:$B,$B12,$A:$A,$K12))) | M12: =IF(OR($K12="",E12=""),"",IF(COUNTIFS($B:$B,$B12,$A:$A,$K12,E:E,">=0")=0,"",E12-SUMIFS(E:E,$B:$B,$B12,$A:$A,$K12))) | N12: =IF(OR($K12="",F12=""),"",IF(COUNTIFS($B:$B,$B12,$A:$A,$K12,F:F,">=0")=0,"",F12-SUMIFS(F:F,$B:$B,$B12,$A:$A,$K12))) | O12: =IF(OR($K12="",G12=""),"",IF(COUNTIFS($B:$B,$B12,$A:$A,$K12,G:G,">=0")=0,"",G12-SUMIFS(G:G,$B:$B,$B12,$A:$A,$K12)))
A13: 46325 | B13: Intel Core i5-12400F | C13: CPU | D13: 140 | H13: =IFERROR(IF(INDEX(Dólar!$B:$B,MATCH(A13,Dólar!$A:$A,0))="","",INDEX(Dólar!$B:$B,MATCH(A13,Dólar!$A:$A,0))),"") | I13: =IFERROR(INDEX(Dólar!$E:$E,MATCH(A13,Dólar!$A:$A,0)),"") | J13: ver anuncio | K13: 46324 | L13: =IF(OR($K13="",D13=""),"",IF(COUNTIFS($B:$B,$B13,$A:$A,$K13,D:D,">=0")=0,"",D13-SUMIFS(D:D,$B:$B,$B13,$A:$A,$K13))) | M13: =IF(OR($K13="",E13=""),"",IF(COUNTIFS($B:$B,$B13,$A:$A,$K13,E:E,">=0")=0,"",E13-SUMIFS(E:E,$B:$B,$B13,$A:$A,$K13))) | N13: =IF(OR($K13="",F13=""),"",IF(COUNTIFS($B:$B,$B13,$A:$A,$K13,F:F,">=0")=0,"",F13-SUMIFS(F:F,$B:$B,$B13,$A:$A,$K13))) | O13: =IF(OR($K13="",G13=""),"",IF(COUNTIFS($B:$B,$B13,$A:$A,$K13,G:G,">=0")=0,"",G13-SUMIFS(G:G,$B:$B,$B13,$A:$A,$K13)))
A14: 46325 | B14: Intel Core Ultra 7 265K | C14: CPU | D14: 248 | H14: =IFERROR(IF(INDEX(Dólar!$B:$B,MATCH(A14,Dólar!$A:$A,0))="","",INDEX(Dólar!$B:$B,MATCH(A14,Dólar!$A:$A,0))),"") | I14: =IFERROR(INDEX(Dólar!$E:$E,MATCH(A14,Dólar!$A:$A,0)),"") | J14: ver anuncio | K14: 46324 | L14: =IF(OR($K14="",D14=""),"",IF(COUNTIFS($B:$B,$B14,$A:$A,$K14,D:D,">=0")=0,"",D14-SUMIFS(D:D,$B:$B,$B14,$A:$A,$K14))) | M14: =IF(OR($K14="",E14=""),"",IF(COUNTIFS($B:$B,$B14,$A:$A,$K14,E:E,">=0")=0,"",E14-SUMIFS(E:E,$B:$B,$B14,$A:$A,$K14))) | N14: =IF(OR($K14="",F14=""),"",IF(COUNTIFS($B:$B,$B14,$A:$A,$K14,F:F,">=0")=0,"",F14-SUMIFS(F:F,$B:$B,$B14,$A:$A,$K14))) | O14: =IF(OR($K14="",G14=""),"",IF(COUNTIFS($B:$B,$B14,$A:$A,$K14,G:G,">=0")=0,"",G14-SUMIFS(G:G,$B:$B,$B14,$A:$A,$K14)))
A15: 46325 | B15: Corsair Vengeance RGB DDR5 32GB (2x16) 6000 | C15: RAM | D15: 450 | F15: 6200 | H15: =IFERROR(IF(INDEX(Dólar!$B:$B,MATCH(A15,Dólar!$A:$A,0))="","",INDEX(Dólar!$B:$B,MATCH(A15,Dólar!$A:$A,0))),"") | I15: =IFERROR(INDEX(Dólar!$E:$E,MATCH(A15,Dólar!$A:$A,0)),"") | J15: ver anuncio | K15: 46324 | L15: =IF(OR($K15="",D15=""),"",IF(COUNTIFS($B:$B,$B15,$A:$A,$K15,D:D,">=0")=0,"",D15-SUMIFS(D:D,$B:$B,$B15,$A:$A,$K15))) | M15: =IF(OR($K15="",E15=""),"",IF(COUNTIFS($B:$B,$B15,$A:$A,$K15,E:E,">=0")=0,"",E15-SUMIFS(E:E,$B:$B,$B15,$A:$A,$K15))) | N15: =IF(OR($K15="",F15=""),"",IF(COUNTIFS($B:$B,$B15,$A:$A,$K15,F:F,">=0")=0,"",F15-SUMIFS(F:F,$B:$B,$B15,$A:$A,$K15))) | O15: =IF(OR($K15="",G15=""),"",IF(COUNTIFS($B:$B,$B15,$A:$A,$K15,G:G,">=0")=0,"",G15-SUMIFS(G:G,$B:$B,$B15,$A:$A,$K15)))
A16: 46325 | B16: Corsair Vengeance RGB DDR5 32GB (2x16) 5600 | C16: RAM | D16: 459 | H16: =IFERROR(IF(INDEX(Dólar!$B:$B,MATCH(A16,Dólar!$A:$A,0))="","",INDEX(Dólar!$B:$B,MATCH(A16,Dólar!$A:$A,0))),"") | I16: =IFERROR(INDEX(Dólar!$E:$E,MATCH(A16,Dólar!$A:$A,0)),"") | J16: ver anuncio | K16: 46324 | L16: =IF(OR($K16="",D16=""),"",IF(COUNTIFS($B:$B,$B16,$A:$A,$K16,D:D,">=0")=0,"",D16-SUMIFS(D:D,$B:$B,$B16,$A:$A,$K16))) | M16: =IF(OR($K16="",E16=""),"",IF(COUNTIFS($B:$B,$B16,$A:$A,$K16,E:E,">=0")=0,"",E16-SUMIFS(E:E,$B:$B,$B16,$A:$A,$K16))) | N16: =IF(OR($K16="",F16=""),"",IF(COUNTIFS($B:$B,$B16,$A:$A,$K16,F:F,">=0")=0,"",F16-SUMIFS(F:F,$B:$B,$B16,$A:$A,$K16))) | O16: =IF(OR($K16="",G16=""),"",IF(COUNTIFS($B:$B,$B16,$A:$A,$K16,G:G,">=0")=0,"",G16-SUMIFS(G:G,$B:$B,$B16,$A:$A,$K16)))
A17: 46324 | B17: SSD NVMe 2TB | C17: SSD | D17: 209.99 | E17: 154.99 | H17: =IFERROR(IF(INDEX(Dólar!$B:$B,MATCH(A17,Dólar!$A:$A,0))="","",INDEX(Dólar!$B:$B,MATCH(A17,Dólar!$A:$A,0))),"") | I17: =IFERROR(INDEX(Dólar!$E:$E,MATCH(A17,Dólar!$A:$A,0)),"") | J17: ver anuncio | K17: 46323 | L17: =IF(OR($K17="",D17=""),"",IF(COUNTIFS($B:$B,$B17,$A:$A,$K17,D:D,">=0")=0,"",D17-SUMIFS(D:D,$B:$B,$B17,$A:$A,$K17))) | M17: =IF(OR($K17="",E17=""),"",IF(COUNTIFS($B:$B,$B17,$A:$A,$K17,E:E,">=0")=0,"",E17-SUMIFS(E:E,$B:$B,$B17,$A:$A,$K17))) | N17: =IF(OR($K17="",F17=""),"",IF(COUNTIFS($B:$B,$B17,$A:$A,$K17,F:F,">=0")=0,"",F17-SUMIFS(F:F,$B:$B,$B17,$A:$A,$K17))) | O17: =IF(OR($K17="",G17=""),"",IF(COUNTIFS($B:$B,$B17,$A:$A,$K17,G:G,">=0")=0,"",G17-SUMIFS(G:G,$B:$B,$B17,$A:$A,$K17)))
A18: 46324 | B18: SSD NVMe 1TB | C18: SSD | D18: 135 | E18: 99 | H18: =IFERROR(IF(INDEX(Dólar!$B:$B,MATCH(A18,Dólar!$A:$A,0))="","",INDEX(Dólar!$B:$B,MATCH(A18,Dólar!$A:$A,0))),"") | I18: =IFERROR(INDEX(Dólar!$E:$E,MATCH(A18,Dólar!$A:$A,0)),"") | J18: ver anuncio | K18: 46323 | L18: =IF(OR($K18="",D18=""),"",IF(COUNTIFS($B:$B,$B18,$A:$A,$K18,D:D,">=0")=0,"",D18-SUMIFS(D:D,$B:$B,$B18,$A:$A,$K18))) | M18: =IF(OR($K18="",E18=""),"",IF(COUNTIFS($B:$B,$B18,$A:$A,$K18,E:E,">=0")=0,"",E18-SUMIFS(E:E,$B:$B,$B18,$A:$A,$K18))) | N18: =IF(OR($K18="",F18=""),"",IF(COUNTIFS($B:$B,$B18,$A:$A,$K18,F:F,">=0")=0,"",F18-SUMIFS(F:F,$B:$B,$B18,$A:$A,$K18))) | O18: =IF(OR($K18="",G18=""),"",IF(COUNTIFS($B:$B,$B18,$A:$A,$K18,G:G,">=0")=0,"",G18-SUMIFS(G:G,$B:$B,$B18,$A:$A,$K18)))
A19: 46324 | B19: Ryzen 9 9950X | C19: CPU | D19: 549.99 | E19: 454.99 | H19: =IFERROR(IF(INDEX(Dólar!$B:$B,MATCH(A19,Dólar!$A:$A,0))="","",INDEX(Dólar!$B:$B,MATCH(A19,Dólar!$A:$A,0))),"") | I19: =IFERROR(INDEX(Dólar!$E:$E,MATCH(A19,Dólar!$A:$A,0)),"") | J19: ver anuncio | K19: 46323 | L19: =IF(OR($K19="",D19=""),"",IF(COUNTIFS($B:$B,$B19,$A:$A,$K19,D:D,">=0")=0,"",D19-SUMIFS(D:D,$B:$B,$B19,$A:$A,$K19))) | M19: =IF(OR($K19="",E19=""),"",IF(COUNTIFS($B:$B,$B19,$A:$A,$K19,E:E,">=0")=0,"",E19-SUMIFS(E:E,$B:$B,$B19,$A:$A,$K19))) | N19: =IF(OR($K19="",F19=""),"",IF(COUNTIFS($B:$B,$B19,$A:$A,$K19,F:F,">=0")=0,"",F19-SUMIFS(F:F,$B:$B,$B19,$A:$A,$K19))) | O19: =IF(OR($K19="",G19=""),"",IF(COUNTIFS($B:$B,$B19,$A:$A,$K19,G:G,">=0")=0,"",G19-SUMIFS(G:G,$B:$B,$B19,$A:$A,$K19)))
A20: 46324 | B20: Ryzen 7 7800X3D | C20: CPU | D20: 325 | E20: 265 | H20: =IFERROR(IF(INDEX(Dólar!$B:$B,MATCH(A20,Dólar!$A:$A,0))="","",INDEX(Dólar!$B:$B,MATCH(A20,Dólar!$A:$A,0))),"") | I20: =IFERROR(INDEX(Dólar!$E:$E,MATCH(A20,Dólar!$A:$A,0)),"") | J20: ver anuncio | K20: 46323 | L20: =IF(OR($K20="",D20=""),"",IF(COUNTIFS($B:$B,$B20,$A:$A,$K20,D:D,">=0")=0,"",D20-SUMIFS(D:D,$B:$B,$B20,$A:$A,$K20))) | M20: =IF(OR($K20="",E20=""),"",IF(COUNTIFS($B:$B,$B20,$A:$A,$K20,E:E,">=0")=0,"",E20-SUMIFS(E:E,$B:$B,$B20,$A:$A,$K20))) | N20: =IF(OR($K20="",F20=""),"",IF(COUNTIFS($B:$B,$B20,$A:$A,$K20,F:F,">=0")=0,"",F20-SUMIFS(F:F,$B:$B,$B20,$A:$A,$K20))) | O20: =IF(OR($K20="",G20=""),"",IF(COUNTIFS($B:$B,$B20,$A:$A,$K20,G:G,">=0")=0,"",G20-SUMIFS(G:G,$B:$B,$B20,$A:$A,$K20)))
A21: 46324 | B21: Ryzen 7 7700X | C21: CPU | D21: 219 | E21: 189.99 | H21: =IFERROR(IF(INDEX(Dólar!$B:$B,MATCH(A21,Dólar!$A:$A,0))="","",INDEX(Dólar!$B:$B,MATCH(A21,Dólar!$A:$A,0))),"") | I21: =IFERROR(INDEX(Dólar!$E:$E,MATCH(A21,Dólar!$A:$A,0)),"") | J21: ver anuncio | K21: 46323 | L21: =IF(OR($K21="",D21=""),"",IF(COUNTIFS($B:$B,$B21,$A:$A,$K21,D:D,">=0")=0,"",D21-SUMIFS(D:D,$B:$B,$B21,$A:$A,$K21))) | M21: =IF(OR($K21="",E21=""),"",IF(COUNTIFS($B:$B,$B21,$A:$A,$K21,E:E,">=0")=0,"",E21-SUMIFS(E:E,$B:$B,$B21,$A:$A,$K21))) | N21: =IF(OR($K21="",F21=""),"",IF(COUNTIFS($B:$B,$B21,$A:$A,$K21,F:F,">=0")=0,"",F21-SUMIFS(F:F,$B:$B,$B21,$A:$A,$K21))) | O21: =IF(OR($K21="",G21=""),"",IF(COUNTIFS($B:$B,$B21,$A:$A,$K21,G:G,">=0")=0,"",G21-SUMIFS(G:G,$B:$B,$B21,$A:$A,$K21)))
A22: 46324 | B22: Ryzen 7 5700X3D | C22: CPU | E22: 336 | H22: =IFERROR(IF(INDEX(Dólar!$B:$B,MATCH(A22,Dólar!$A:$A,0))="","",INDEX(Dólar!$B:$B,MATCH(A22,Dólar!$A:$A,0))),"") | I22: =IFERROR(INDEX(Dólar!$E:$E,MATCH(A22,Dólar!$A:$A,0)),"") | J22: ver anuncio | K22: 46323 | L22: =IF(OR($K22="",D22=""),"",IF(COUNTIFS($B:$B,$B22,$A:$A,$K22,D:D,">=0")=0,"",D22-SUMIFS(D:D,$B:$B,$B22,$A:$A,$K22))) | M22: =IF(OR($K22="",E22=""),"",IF(COUNTIFS($B:$B,$B22,$A:$A,$K22,E:E,">=0")=0,"",E22-SUMIFS(E:E,$B:$B,$B22,$A:$A,$K22))) | N22: =IF(OR($K22="",F22=""),"",IF(COUNTIFS($B:$B,$B22,$A:$A,$K22,F:F,">=0")=0,"",F22-SUMIFS(F:F,$B:$B,$B22,$A:$A,$K22))) | O22: =IF(OR($K22="",G22=""),"",IF(COUNTIFS($B:$B,$B22,$A:$A,$K22,G:G,">=0")=0,"",G22-SUMIFS(G:G,$B:$B,$B22,$A:$A,$K22)))
A23: 46324 | B23: Ryzen 5 7600 | C23: CPU | D23: 199.99 | E23: 114.99 | H23: =IFERROR(IF(INDEX(Dólar!$B:$B,MATCH(A23,Dólar!$A:$A,0))="","",INDEX(Dólar!$B:$B,MATCH(A23,Dólar!$A:$A,0))),"") | I23: =IFERROR(INDEX(Dólar!$E:$E,MATCH(A23,Dólar!$A:$A,0)),"") | J23: ver anuncio | K23: 46323 | L23: =IF(OR($K23="",D23=""),"",IF(COUNTIFS($B:$B,$B23,$A:$A,$K23,D:D,">=0")=0,"",D23-SUMIFS(D:D,$B:$B,$B23,$A:$A,$K23))) | M23: =IF(OR($K23="",E23=""),"",IF(COUNTIFS($B:$B,$B23,$A:$A,$K23,E:E,">=0")=0,"",E23-SUMIFS(E:E,$B:$B,$B23,$A:$A,$K23))) | N23: =IF(OR($K23="",F23=""),"",IF(COUNTIFS($B:$B,$B23,$A:$A,$K23,F:F,">=0")=0,"",F23-SUMIFS(F:F,$B:$B,$B23,$A:$A,$K23))) | O23: =IF(OR($K23="",G23=""),"",IF(COUNTIFS($B:$B,$B23,$A:$A,$K23,G:G,">=0")=0,"",G23-SUMIFS(G:G,$B:$B,$B23,$A:$A,$K23)))
A24: 46324 | B24: Ryzen 5 7500F | C24: CPU | D24: 135.6 | E24: 114.99 | H24: =IFERROR(IF(INDEX(Dólar!$B:$B,MATCH(A24,Dólar!$A:$A,0))="","",INDEX(Dólar!$B:$B,MATCH(A24,Dólar!$A:$A,0))),"") | I24: =IFERROR(INDEX(Dólar!$E:$E,MATCH(A24,Dólar!$A:$A,0)),"") | J24: ver anuncio | K24: 46323 | L24: =IF(OR($K24="",D24=""),"",IF(COUNTIFS($B:$B,$B24,$A:$A,$K24,D:D,">=0")=0,"",D24-SUMIFS(D:D,$B:$B,$B24,$A:$A,$K24))) | M24: =IF(OR($K24="",E24=""),"",IF(COUNTIFS($B:$B,$B24,$A:$A,$K24,E:E,">=0")=0,"",E24-SUMIFS(E:E,$B:$B,$B24,$A:$A,$K24))) | N24: =IF(OR($K24="",F24=""),"",IF(COUNTIFS($B:$B,$B24,$A:$A,$K24,F:F,">=0")=0,"",F24-SUMIFS(F:F,$B:$B,$B24,$A:$A,$K24))) | O24: =IF(OR($K24="",G24=""),"",IF(COUNTIFS($B:$B,$B24,$A:$A,$K24,G:G,">=0")=0,"",G24-SUMIFS(G:G,$B:$B,$B24,$A:$A,$K24)))
A25: 46324 | B25: Ryzen 5 5600 | C25: CPU | D25: 138.9 | E25: 131.99 | H25: =IFERROR(IF(INDEX(Dólar!$B:$B,MATCH(A25,Dólar!$A:$A,0))="","",INDEX(Dólar!$B:$B,MATCH(A25,Dólar!$A:$A,0))),"") | I25: =IFERROR(INDEX(Dólar!$E:$E,MATCH(A25,Dólar!$A:$A,0)),"") | J25: ver anuncio | K25: 46323 | L25: =IF(OR($K25="",D25=""),"",IF(COUNTIFS($B:$B,$B25,$A:$A,$K25,D:D,">=0")=0,"",D25-SUMIFS(D:D,$B:$B,$B25,$A:$A,$K25))) | M25: =IF(OR($K25="",E25=""),"",IF(COUNTIFS($B:$B,$B25,$A:$A,$K25,E:E,">=0")=0,"",E25-SUMIFS(E:E,$B:$B,$B25,$A:$A,$K25))) | N25: =IF(OR($K25="",F25=""),"",IF(COUNTIFS($B:$B,$B25,$A:$A,$K25,F:F,">=0")=0,"",F25-SUMIFS(F:F,$B:$B,$B25,$A:$A,$K25))) | O25: =IF(OR($K25="",G25=""),"",IF(COUNTIFS($B:$B,$B25,$A:$A,$K25,G:G,">=0")=0,"",G25-SUMIFS(G:G,$B:$B,$B25,$A:$A,$K25)))
A26: 46324 | B26: RAM DDR4 16GB (2x8) 3200 | C26: RAM | D26: 89.99 | E26: 59.99 | H26: =IFERROR(IF(INDEX(Dólar!$B:$B,MATCH(A26,Dólar!$A:$A,0))="","",INDEX(Dólar!$B:$B,MATCH(A26,Dólar!$A:$A,0))),"") | I26: =IFERROR(INDEX(Dólar!$E:$E,MATCH(A26,Dólar!$A:$A,0)),"") | J26: ver anuncio | K26: 46323 | L26: =IF(OR($K26="",D26=""),"",IF(COUNTIFS($B:$B,$B26,$A:$A,$K26,D:D,">=0")=0,"",D26-SUMIFS(D:D,$B:$B,$B26,$A:$A,$K26))) | M26: =IF(OR($K26="",E26=""),"",IF(COUNTIFS($B:$B,$B26,$A:$A,$K26,E:E,">=0")=0,"",E26-SUMIFS(E:E,$B:$B,$B26,$A:$A,$K26))) | N26: =IF(OR($K26="",F26=""),"",IF(COUNTIFS($B:$B,$B26,$A:$A,$K26,F:F,">=0")=0,"",F26-SUMIFS(F:F,$B:$B,$B26,$A:$A,$K26))) | O26: =IF(OR($K26="",G26=""),"",IF(COUNTIFS($B:$B,$B26,$A:$A,$K26,G:G,">=0")=0,"",G26-SUMIFS(G:G,$B:$B,$B26,$A:$A,$K26)))
A27: 46324 | B27: Intel Core i5-14400F | C27: CPU | D27: 164.49 | E27: 130 | H27: =IFERROR(IF(INDEX(Dólar!$B:$B,MATCH(A27,Dólar!$A:$A,0))="","",INDEX(Dólar!$B:$B,MATCH(A27,Dólar!$A:$A,0))),"") | I27: =IFERROR(INDEX(Dólar!$E:$E,MATCH(A27,Dólar!$A:$A,0)),"") | J27: ver anuncio | K27: 46323 | L27: =IF(OR($K27="",D27=""),"",IF(COUNTIFS($B:$B,$B27,$A:$A,$K27,D:D,">=0")=0,"",D27-SUMIFS(D:D,$B:$B,$B27,$A:$A,$K27))) | M27: =IF(OR($K27="",E27=""),"",IF(COUNTIFS($B:$B,$B27,$A:$A,$K27,E:E,">=0")=0,"",E27-SUMIFS(E:E,$B:$B,$B27,$A:$A,$K27))) | N27: =IF(OR($K27="",F27=""),"",IF(COUNTIFS($B:$B,$B27,$A:$A,$K27,F:F,">=0")=0,"",F27-SUMIFS(F:F,$B:$B,$B27,$A:$A,$K27))) | O27: =IF(OR($K27="",G27=""),"",IF(COUNTIFS($B:$B,$B27,$A:$A,$K27,G:G,">=0")=0,"",G27-SUMIFS(G:G,$B:$B,$B27,$A:$A,$K27)))
A28: 46324 | B28: Intel Core i5-13400 | C28: CPU | E28: 129.99 | H28: =IFERROR(IF(INDEX(Dólar!$B:$B,MATCH(A28,Dólar!$A:$A,0))="","",INDEX(Dólar!$B:$B,MATCH(A28,Dólar!$A:$A,0))),"") | I28: =IFERROR(INDEX(Dólar!$E:$E,MATCH(A28,Dólar!$A:$A,0)),"") | J28: ver anuncio | K28: 46323 | L28: =IF(OR($K28="",D28=""),"",IF(COUNTIFS($B:$B,$B28,$A:$A,$K28,D:D,">=0")=0,"",D28-SUMIFS(D:D,$B:$B,$B28,$A:$A,$K28))) | M28: =IF(OR($K28="",E28=""),"",IF(COUNTIFS($B:$B,$B28,$A:$A,$K28,E:E,">=0")=0,"",E28-SUMIFS(E:E,$B:$B,$B28,$A:$A,$K28))) | N28: =IF(OR($K28="",F28=""),"",IF(COUNTIFS($B:$B,$B28,$A:$A,$K28,F:F,">=0")=0,"",F28-SUMIFS(F:F,$B:$B,$B28,$A:$A,$K28))) | O28: =IF(OR($K28="",G28=""),"",IF(COUNTIFS($B:$B,$B28,$A:$A,$K28,G:G,">=0")=0,"",G28-SUMIFS(G:G,$B:$B,$B28,$A:$A,$K28)))
A29: 46324 | B29: Intel Core i5-12400F | C29: CPU | D29: 140 | E29: 119.99 | H29: =IFERROR(IF(INDEX(Dólar!$B:$B,MATCH(A29,Dólar!$A:$A,0))="","",INDEX(Dólar!$B:$B,MATCH(A29,Dólar!$A:$A,0))),"") | I29: =IFERROR(INDEX(Dólar!$E:$E,MATCH(A29,Dólar!$A:$A,0)),"") | J29: ver anuncio | K29: 46323 | L29: =IF(OR($K29="",D29=""),"",IF(COUNTIFS($B:$B,$B29,$A:$A,$K29,D:D,">=0")=0,"",D29-SUMIFS(D:D,$B:$B,$B29,$A:$A,$K29))) | M29: =IF(OR($K29="",E29=""),"",IF(COUNTIFS($B:$B,$B29,$A:$A,$K29,E:E,">=0")=0,"",E29-SUMIFS(E:E,$B:$B,$B29,$A:$A,$K29))) | N29: =IF(OR($K29="",F29=""),"",IF(COUNTIFS($B:$B,$B29,$A:$A,$K29,F:F,">=0")=0,"",F29-SUMIFS(F:F,$B:$B,$B29,$A:$A,$K29))) | O29: =IF(OR($K29="",G29=""),"",IF(COUNTIFS($B:$B,$B29,$A:$A,$K29,G:G,">=0")=0,"",G29-SUMIFS(G:G,$B:$B,$B29,$A:$A,$K29)))
A30: 46324 | B30: Intel Core Ultra 7 265K | C30: CPU | D30: 259.99 | E30: 249.99 | H30: =IFERROR(IF(INDEX(Dólar!$B:$B,MATCH(A30,Dólar!$A:$A,0))="","",INDEX(Dólar!$B:$B,MATCH(A30,Dólar!$A:$A,0))),"") | I30: =IFERROR(INDEX(Dólar!$E:$E,MATCH(A30,Dólar!$A:$A,0)),"") | J30: ver anuncio | K30: 46323 | L30: =IF(OR($K30="",D30=""),"",IF(COUNTIFS($B:$B,$B30,$A:$A,$K30,D:D,">=0")=0,"",D30-SUMIFS(D:D,$B:$B,$B30,$A:$A,$K30))) | M30: =IF(OR($K30="",E30=""),"",IF(COUNTIFS($B:$B,$B30,$A:$A,$K30,E:E,">=0")=0,"",E30-SUMIFS(E:E,$B:$B,$B30,$A:$A,$K30))) | N30: =IF(OR($K30="",F30=""),"",IF(COUNTIFS($B:$B,$B30,$A:$A,$K30,F:F,">=0")=0,"",F30-SUMIFS(F:F,$B:$B,$B30,$A:$A,$K30))) | O30: =IF(OR($K30="",G30=""),"",IF(COUNTIFS($B:$B,$B30,$A:$A,$K30,G:G,">=0")=0,"",G30-SUMIFS(G:G,$B:$B,$B30,$A:$A,$K30)))
A31: 46324 | B31: Corsair Vengeance RGB DDR5 32GB (2x16) 6000 | C31: RAM | D31: 450 | E31: 419.99 | H31: =IFERROR(IF(INDEX(Dólar!$B:$B,MATCH(A31,Dólar!$A:$A,0))="","",INDEX(Dólar!$B:$B,MATCH(A31,Dólar!$A:$A,0))),"") | I31: =IFERROR(INDEX(Dólar!$E:$E,MATCH(A31,Dólar!$A:$A,0)),"") | J31: ver anuncio | K31: 46323 | L31: =IF(OR($K31="",D31=""),"",IF(COUNTIFS($B:$B,$B31,$A:$A,$K31,D:D,">=0")=0,"",D31-SUMIFS(D:D,$B:$B,$B31,$A:$A,$K31))) | M31: =IF(OR($K31="",E31=""),"",IF(COUNTIFS($B:$B,$B31,$A:$A,$K31,E:E,">=0")=0,"",E31-SUMIFS(E:E,$B:$B,$B31,$A:$A,$K31))) | N31: =IF(OR($K31="",F31=""),"",IF(COUNTIFS($B:$B,$B31,$A:$A,$K31,F:F,">=0")=0,"",F31-SUMIFS(F:F,$B:$B,$B31,$A:$A,$K31))) | O31: =IF(OR($K31="",G31=""),"",IF(COUNTIFS($B:$B,$B31,$A:$A,$K31,G:G,">=0")=0,"",G31-SUMIFS(G:G,$B:$B,$B31,$A:$A,$K31)))
A32: 46324 | B32: Corsair Vengeance RGB DDR5 32GB (2x16) 5600 | C32: RAM | D32: 459 | E32: 389.99 | H32: =IFERROR(IF(INDEX(Dólar!$B:$B,MATCH(A32,Dólar!$A:$A,0))="","",INDEX(Dólar!$B:$B,MATCH(A32,Dólar!$A:$A,0))),"") | I32: =IFERROR(INDEX(Dólar!$E:$E,MATCH(A32,Dólar!$A:$A,0)),"") | J32: ver anuncio | K32: 46323 | L32: =IF(OR($K32="",D32=""),"",IF(COUNTIFS($B:$B,$B32,$A:$A,$K32,D:D,">=0")=0,"",D32-SUMIFS(D:D,$B:$B,$B32,$A:$A,$K32))) | M32: =IF(OR($K32="",E32=""),"",IF(COUNTIFS($B:$B,$B32,$A:$A,$K32,E:E,">=0")=0,"",E32-SUMIFS(E:E,$B:$B,$B32,$A:$A,$K32))) | N32: =IF(OR($K32="",F32=""),"",IF(COUNTIFS($B:$B,$B32,$A:$A,$K32,F:F,">=0")=0,"",F32-SUMIFS(F:F,$B:$B,$B32,$A:$A,$K32))) | O32: =IF(OR($K32="",G32=""),"",IF(COUNTIFS($B:$B,$B32,$A:$A,$K32,G:G,">=0")=0,"",G32-SUMIFS(G:G,$B:$B,$B32,$A:$A,$K32)))
A33: 46323 | B33: SSD NVMe 2TB | C33: SSD | D33: 185 | E33: 179.99 | H33: =IFERROR(IF(INDEX(Dólar!$B:$B,MATCH(A33,Dólar!$A:$A,0))="","",INDEX(Dólar!$B:$B,MATCH(A33,Dólar!$A:$A,0))),"") | I33: =IFERROR(INDEX(Dólar!$E:$E,MATCH(A33,Dólar!$A:$A,0)),"") | J33: ver anuncio | K33: 46322 | L33: =IF(OR($K33="",D33=""),"",IF(COUNTIFS($B:$B,$B33,$A:$A,$K33,D:D,">=0")=0,"",D33-SUMIFS(D:D,$B:$B,$B33,$A:$A,$K33))) | M33: =IF(OR($K33="",E33=""),"",IF(COUNTIFS($B:$B,$B33,$A:$A,$K33,E:E,">=0")=0,"",E33-SUMIFS(E:E,$B:$B,$B33,$A:$A,$K33))) | N33: =IF(OR($K33="",F33=""),"",IF(COUNTIFS($B:$B,$B33,$A:$A,$K33,F:F,">=0")=0,"",F33-SUMIFS(F:F,$B:$B,$B33,$A:$A,$K33))) | O33: =IF(OR($K33="",G33=""),"",IF(COUNTIFS($B:$B,$B33,$A:$A,$K33,G:G,">=0")=0,"",G33-SUMIFS(G:G,$B:$B,$B33,$A:$A,$K33)))
A34: 46323 | B34: SSD NVMe 1TB | C34: SSD | D34: 114.99 | E34: 85 | F34: 1100 | H34: =IFERROR(IF(INDEX(Dólar!$B:$B,MATCH(A34,Dólar!$A:$A,0))="","",INDEX(Dólar!$B:$B,MATCH(A34,Dólar!$A:$A,0))),"") | I34: =IFERROR(INDEX(Dólar!$E:$E,MATCH(A34,Dólar!$A:$A,0)),"") | J34: ver anuncio | K34: 46322 | L34: =IF(OR($K34="",D34=""),"",IF(COUNTIFS($B:$B,$B34,$A:$A,$K34,D:D,">=0")=0,"",D34-SUMIFS(D:D,$B:$B,$B34,$A:$A,$K34))) | M34: =IF(OR($K34="",E34=""),"",IF(COUNTIFS($B:$B,$B34,$A:$A,$K34,E:E,">=0")=0,"",E34-SUMIFS(E:E,$B:$B,$B34,$A:$A,$K34))) | N34: =IF(OR($K34="",F34=""),"",IF(COUNTIFS($B:$B,$B34,$A:$A,$K34,F:F,">=0")=0,"",F34-SUMIFS(F:F,$B:$B,$B34,$A:$A,$K34))) | O34: =IF(OR($K34="",G34=""),"",IF(COUNTIFS($B:$B,$B34,$A:$A,$K34,G:G,">=0")=0,"",G34-SUMIFS(G:G,$B:$B,$B34,$A:$A,$K34)))
A35: 46323 | B35: Ryzen 9 9950X | C35: CPU | D35: 549.99 | E35: 454.99 | H35: =IFERROR(IF(INDEX(Dólar!$B:$B,MATCH(A35,Dólar!$A:$A,0))="","",INDEX(Dólar!$B:$B,MATCH(A35,Dólar!$A:$A,0))),"") | I35: =IFERROR(INDEX(Dólar!$E:$E,MATCH(A35,Dólar!$A:$A,0)),"") | J35: ver anuncio | K35: 46322 | L35: =IF(OR($K35="",D35=""),"",IF(COUNTIFS($B:$B,$B35,$A:$A,$K35,D:D,">=0")=0,"",D35-SUMIFS(D:D,$B:$B,$B35,$A:$A,$K35))) | M35: =IF(OR($K35="",E35=""),"",IF(COUNTIFS($B:$B,$B35,$A:$A,$K35,E:E,">=0")=0,"",E35-SUMIFS(E:E,$B:$B,$B35,$A:$A,$K35))) | N35: =IF(OR($K35="",F35=""),"",IF(COUNTIFS($B:$B,$B35,$A:$A,$K35,F:F,">=0")=0,"",F35-SUMIFS(F:F,$B:$B,$B35,$A:$A,$K35))) | O35: =IF(OR($K35="",G35=""),"",IF(COUNTIFS($B:$B,$B35,$A:$A,$K35,G:G,">=0")=0,"",G35-SUMIFS(G:G,$B:$B,$B35,$A:$A,$K35)))
A36: 46323 | B36: Ryzen 7 7800X3D | C36: CPU | D36: 325 | E36: 275 | H36: =IFERROR(IF(INDEX(Dólar!$B:$B,MATCH(A36,Dólar!$A:$A,0))="","",INDEX(Dólar!$B:$B,MATCH(A36,Dólar!$A:$A,0))),"") | I36: =IFERROR(INDEX(Dólar!$E:$E,MATCH(A36,Dólar!$A:$A,0)),"") | J36: ver anuncio | K36: 46322 | L36: =IF(OR($K36="",D36=""),"",IF(COUNTIFS($B:$B,$B36,$A:$A,$K36,D:D,">=0")=0,"",D36-SUMIFS(D:D,$B:$B,$B36,$A:$A,$K36))) | M36: =IF(OR($K36="",E36=""),"",IF(COUNTIFS($B:$B,$B36,$A:$A,$K36,E:E,">=0")=0,"",E36-SUMIFS(E:E,$B:$B,$B36,$A:$A,$K36))) | N36: =IF(OR($K36="",F36=""),"",IF(COUNTIFS($B:$B,$B36,$A:$A,$K36,F:F,">=0")=0,"",F36-SUMIFS(F:F,$B:$B,$B36,$A:$A,$K36))) | O36: =IF(OR($K36="",G36=""),"",IF(COUNTIFS($B:$B,$B36,$A:$A,$K36,G:G,">=0")=0,"",G36-SUMIFS(G:G,$B:$B,$B36,$A:$A,$K36)))
A37: 46323 | B37: Ryzen 7 7700X | C37: CPU | D37: 219 | E37: 189.99 | F37: 4000 | H37: =IFERROR(IF(INDEX(Dólar!$B:$B,MATCH(A37,Dólar!$A:$A,0))="","",INDEX(Dólar!$B:$B,MATCH(A37,Dólar!$A:$A,0))),"") | I37: =IFERROR(INDEX(Dólar!$E:$E,MATCH(A37,Dólar!$A:$A,0)),"") | J37: ver anuncio | K37: 46322 | L37: =IF(OR($K37="",D37=""),"",IF(COUNTIFS($B:$B,$B37,$A:$A,$K37,D:D,">=0")=0,"",D37-SUMIFS(D:D,$B:$B,$B37,$A:$A,$K37))) | M37: =IF(OR($K37="",E37=""),"",IF(COUNTIFS($B:$B,$B37,$A:$A,$K37,E:E,">=0")=0,"",E37-SUMIFS(E:E,$B:$B,$B37,$A:$A,$K37))) | N37: =IF(OR($K37="",F37=""),"",IF(COUNTIFS($B:$B,$B37,$A:$A,$K37,F:F,">=0")=0,"",F37-SUMIFS(F:F,$B:$B,$B37,$A:$A,$K37))) | O37: =IF(OR($K37="",G37=""),"",IF(COUNTIFS($B:$B,$B37,$A:$A,$K37,G:G,">=0")=0,"",G37-SUMIFS(G:G,$B:$B,$B37,$A:$A,$K37)))
A38: 46323 | B38: Ryzen 7 5700X3D | C38: CPU | E38: 336 | H38: =IFERROR(IF(INDEX(Dólar!$B:$B,MATCH(A38,Dólar!$A:$A,0))="","",INDEX(Dólar!$B:$B,MATCH(A38,Dólar!$A:$A,0))),"") | I38: =IFERROR(INDEX(Dólar!$E:$E,MATCH(A38,Dólar!$A:$A,0)),"") | J38: ver anuncio | K38: 46322 | L38: =IF(OR($K38="",D38=""),"",IF(COUNTIFS($B:$B,$B38,$A:$A,$K38,D:D,">=0")=0,"",D38-SUMIFS(D:D,$B:$B,$B38,$A:$A,$K38))) | M38: =IF(OR($K38="",E38=""),"",IF(COUNTIFS($B:$B,$B38,$A:$A,$K38,E:E,">=0")=0,"",E38-SUMIFS(E:E,$B:$B,$B38,$A:$A,$K38))) | N38: =IF(OR($K38="",F38=""),"",IF(COUNTIFS($B:$B,$B38,$A:$A,$K38,F:F,">=0")=0,"",F38-SUMIFS(F:F,$B:$B,$B38,$A:$A,$K38))) | O38: =IF(OR($K38="",G38=""),"",IF(COUNTIFS($B:$B,$B38,$A:$A,$K38,G:G,">=0")=0,"",G38-SUMIFS(G:G,$B:$B,$B38,$A:$A,$K38)))
A39: 46323 | B39: Ryzen 5 7600 | C39: CPU | D39: 146.98 | E39: 119 | H39: =IFERROR(IF(INDEX(Dólar!$B:$B,MATCH(A39,Dólar!$A:$A,0))="","",INDEX(Dólar!$B:$B,MATCH(A39,Dólar!$A:$A,0))),"") | I39: =IFERROR(INDEX(Dólar!$E:$E,MATCH(A39,Dólar!$A:$A,0)),"") | J39: ver anuncio | K39: 46322 | L39: =IF(OR($K39="",D39=""),"",IF(COUNTIFS($B:$B,$B39,$A:$A,$K39,D:D,">=0")=0,"",D39-SUMIFS(D:D,$B:$B,$B39,$A:$A,$K39))) | M39: =IF(OR($K39="",E39=""),"",IF(COUNTIFS($B:$B,$B39,$A:$A,$K39,E:E,">=0")=0,"",E39-SUMIFS(E:E,$B:$B,$B39,$A:$A,$K39))) | N39: =IF(OR($K39="",F39=""),"",IF(COUNTIFS($B:$B,$B39,$A:$A,$K39,F:F,">=0")=0,"",F39-SUMIFS(F:F,$B:$B,$B39,$A:$A,$K39))) | O39: =IF(OR($K39="",G39=""),"",IF(COUNTIFS($B:$B,$B39,$A:$A,$K39,G:G,">=0")=0,"",G39-SUMIFS(G:G,$B:$B,$B39,$A:$A,$K39)))
A40: 46323 | B40: Ryzen 5 7500F | C40: CPU | D40: 135.6 | E40: 129.99 | H40: =IFERROR(IF(INDEX(Dólar!$B:$B,MATCH(A40,Dólar!$A:$A,0))="","",INDEX(Dólar!$B:$B,MATCH(A40,Dólar!$A:$A,0))),"") | I40: =IFERROR(INDEX(Dólar!$E:$E,MATCH(A40,Dólar!$A:$A,0)),"") | J40: ver anuncio | K40: 46322 | L40: =IF(OR($K40="",D40=""),"",IF(COUNTIFS($B:$B,$B40,$A:$A,$K40,D:D,">=0")=0,"",D40-SUMIFS(D:D,$B:$B,$B40,$A:$A,$K40))) | M40: =IF(OR($K40="",E40=""),"",IF(COUNTIFS($B:$B,$B40,$A:$A,$K40,E:E,">=0")=0,"",E40-SUMIFS(E:E,$B:$B,$B40,$A:$A,$K40))) | N40: =IF(OR($K40="",F40=""),"",IF(COUNTIFS($B:$B,$B40,$A:$A,$K40,F:F,">=0")=0,"",F40-SUMIFS(F:F,$B:$B,$B40,$A:$A,$K40))) | O40: =IF(OR($K40="",G40=""),"",IF(COUNTIFS($B:$B,$B40,$A:$A,$K40,G:G,">=0")=0,"",G40-SUMIFS(G:G,$B:$B,$B40,$A:$A,$K40)))
A41: 46323 | B41: Ryzen 5 5600 | C41: CPU | D41: 138.9 | E41: 131.99 | H41: =IFERROR(IF(INDEX(Dólar!$B:$B,MATCH(A41,Dólar!$A:$A,0))="","",INDEX(Dólar!$B:$B,MATCH(A41,Dólar!$A:$A,0))),"") | I41: =IFERROR(INDEX(Dólar!$E:$E,MATCH(A41,Dólar!$A:$A,0)),"") | J41: ver anuncio | K41: 46322 | L41: =IF(OR($K41="",D41=""),"",IF(COUNTIFS($B:$B,$B41,$A:$A,$K41,D:D,">=0")=0,"",D41-SUMIFS(D:D,$B:$B,$B41,$A:$A,$K41))) | M41: =IF(OR($K41="",E41=""),"",IF(COUNTIFS($B:$B,$B41,$A:$A,$K41,E:E,">=0")=0,"",E41-SUMIFS(E:E,$B:$B,$B41,$A:$A,$K41))) | N41: =IF(OR($K41="",F41=""),"",IF(COUNTIFS($B:$B,$B41,$A:$A,$K41,F:F,">=0")=0,"",F41-SUMIFS(F:F,$B:$B,$B41,$A:$A,$K41))) | O41: =IF(OR($K41="",G41=""),"",IF(COUNTIFS($B:$B,$B41,$A:$A,$K41,G:G,">=0")=0,"",G41-SUMIFS(G:G,$B:$B,$B41,$A:$A,$K41)))
A42: 46323 | B42: RAM DDR4 16GB (2x8) 3200 | C42: RAM | D42: 100 | E42: 59.99 | H42: =IFERROR(IF(INDEX(Dólar!$B:$B,MATCH(A42,Dólar!$A:$A,0))="","",INDEX(Dólar!$B:$B,MATCH(A42,Dólar!$A:$A,0))),"") | I42: =IFERROR(INDEX(Dólar!$E:$E,MATCH(A42,Dólar!$A:$A,0)),"") | J42: ver anuncio | K42: 46322 | L42: =IF(OR($K42="",D42=""),"",IF(COUNTIFS($B:$B,$B42,$A:$A,$K42,D:D,">=0")=0,"",D42-SUMIFS(D:D,$B:$B,$B42,$A:$A,$K42))) | M42: =IF(OR($K42="",E42=""),"",IF(COUNTIFS($B:$B,$B42,$A:$A,$K42,E:E,">=0")=0,"",E42-SUMIFS(E:E,$B:$B,$B42,$A:$A,$K42))) | N42: =IF(OR($K42="",F42=""),"",IF(COUNTIFS($B:$B,$B42,$A:$A,$K42,F:F,">=0")=0,"",F42-SUMIFS(F:F,$B:$B,$B42,$A:$A,$K42))) | O42: =IF(OR($K42="",G42=""),"",IF(COUNTIFS($B:$B,$B42,$A:$A,$K42,G:G,">=0")=0,"",G42-SUMIFS(G:G,$B:$B,$B42,$A:$A,$K42)))
A43: 46323 | B43: Intel Core i5-14400F | C43: CPU | D43: 164.49 | E43: 129.99 | H43: =IFERROR(IF(INDEX(Dólar!$B:$B,MATCH(A43,Dólar!$A:$A,0))="","",INDEX(Dólar!$B:$B,MATCH(A43,Dólar!$A:$A,0))),"") | I43: =IFERROR(INDEX(Dólar!$E:$E,MATCH(A43,Dólar!$A:$A,0)),"") | J43: ver anuncio | K43: 46322 | L43: =IF(OR($K43="",D43=""),"",IF(COUNTIFS($B:$B,$B43,$A:$A,$K43,D:D,">=0")=0,"",D43-SUMIFS(D:D,$B:$B,$B43,$A:$A,$K43))) | M43: =IF(OR($K43="",E43=""),"",IF(COUNTIFS($B:$B,$B43,$A:$A,$K43,E:E,">=0")=0,"",E43-SUMIFS(E:E,$B:$B,$B43,$A:$A,$K43))) | N43: =IF(OR($K43="",F43=""),"",IF(COUNTIFS($B:$B,$B43,$A:$A,$K43,F:F,">=0")=0,"",F43-SUMIFS(F:F,$B:$B,$B43,$A:$A,$K43))) | O43: =IF(OR($K43="",G43=""),"",IF(COUNTIFS($B:$B,$B43,$A:$A,$K43,G:G,">=0")=0,"",G43-SUMIFS(G:G,$B:$B,$B43,$A:$A,$K43)))
A44: 46323 | B44: Intel Core i5-13400 | C44: CPU | E44: 149.99 | H44: =IFERROR(IF(INDEX(Dólar!$B:$B,MATCH(A44,Dólar!$A:$A,0))="","",INDEX(Dólar!$B:$B,MATCH(A44,Dólar!$A:$A,0))),"") | I44: =IFERROR(INDEX(Dólar!$E:$E,MATCH(A44,Dólar!$A:$A,0)),"") | J44: ver anuncio | K44: 46322 | L44: =IF(OR($K44="",D44=""),"",IF(COUNTIFS($B:$B,$B44,$A:$A,$K44,D:D,">=0")=0,"",D44-SUMIFS(D:D,$B:$B,$B44,$A:$A,$K44))) | M44: =IF(OR($K44="",E44=""),"",IF(COUNTIFS($B:$B,$B44,$A:$A,$K44,E:E,">=0")=0,"",E44-SUMIFS(E:E,$B:$B,$B44,$A:$A,$K44))) | N44: =IF(OR($K44="",F44=""),"",IF(COUNTIFS($B:$B,$B44,$A:$A,$K44,F:F,">=0")=0,"",F44-SUMIFS(F:F,$B:$B,$B44,$A:$A,$K44))) | O44: =IF(OR($K44="",G44=""),"",IF(COUNTIFS($B:$B,$B44,$A:$A,$K44,G:G,">=0")=0,"",G44-SUMIFS(G:G,$B:$B,$B44,$A:$A,$K44)))
A45: 46323 | B45: Intel Core i5-12400F | C45: CPU | D45: 140 | E45: 124.85 | H45: =IFERROR(IF(INDEX(Dólar!$B:$B,MATCH(A45,Dólar!$A:$A,0))="","",INDEX(Dólar!$B:$B,MATCH(A45,Dólar!$A:$A,0))),"") | I45: =IFERROR(INDEX(Dólar!$E:$E,MATCH(A45,Dólar!$A:$A,0)),"") | J45: ver anuncio | K45: 46322 | L45: =IF(OR($K45="",D45=""),"",IF(COUNTIFS($B:$B,$B45,$A:$A,$K45,D:D,">=0")=0,"",D45-SUMIFS(D:D,$B:$B,$B45,$A:$A,$K45))) | M45: =IF(OR($K45="",E45=""),"",IF(COUNTIFS($B:$B,$B45,$A:$A,$K45,E:E,">=0")=0,"",E45-SUMIFS(E:E,$B:$B,$B45,$A:$A,$K45))) | N45: =IF(OR($K45="",F45=""),"",IF(COUNTIFS($B:$B,$B45,$A:$A,$K45,F:F,">=0")=0,"",F45-SUMIFS(F:F,$B:$B,$B45,$A:$A,$K45))) | O45: =IF(OR($K45="",G45=""),"",IF(COUNTIFS($B:$B,$B45,$A:$A,$K45,G:G,">=0")=0,"",G45-SUMIFS(G:G,$B:$B,$B45,$A:$A,$K45)))
A46: 46323 | B46: Intel Core Ultra 7 265K | C46: CPU | D46: 250 | H46: =IFERROR(IF(INDEX(Dólar!$B:$B,MATCH(A46,Dólar!$A:$A,0))="","",INDEX(Dólar!$B:$B,MATCH(A46,Dólar!$A:$A,0))),"") | I46: =IFERROR(INDEX(Dólar!$E:$E,MATCH(A46,Dólar!$A:$A,0)),"") | J46: ver anuncio | K46: 46322 | L46: =IF(OR($K46="",D46=""),"",IF(COUNTIFS($B:$B,$B46,$A:$A,$K46,D:D,">=0")=0,"",D46-SUMIFS(D:D,$B:$B,$B46,$A:$A,$K46))) | M46: =IF(OR($K46="",E46=""),"",IF(COUNTIFS($B:$B,$B46,$A:$A,$K46,E:E,">=0")=0,"",E46-SUMIFS(E:E,$B:$B,$B46,$A:$A,$K46))) | N46: =IF(OR($K46="",F46=""),"",IF(COUNTIFS($B:$B,$B46,$A:$A,$K46,F:F,">=0")=0,"",F46-SUMIFS(F:F,$B:$B,$B46,$A:$A,$K46))) | O46: =IF(OR($K46="",G46=""),"",IF(COUNTIFS($B:$B,$B46,$A:$A,$K46,G:G,">=0")=0,"",G46-SUMIFS(G:G,$B:$B,$B46,$A:$A,$K46)))
A47: 46323 | B47: Corsair Vengeance RGB DDR5 32GB (2x16) 6000 | C47: RAM | D47: 450 | E47: 399.99 | H47: =IFERROR(IF(INDEX(Dólar!$B:$B,MATCH(A47,Dólar!$A:$A,0))="","",INDEX(Dólar!$B:$B,MATCH(A47,Dólar!$A:$A,0))),"") | I47: =IFERROR(INDEX(Dólar!$E:$E,MATCH(A47,Dólar!$A:$A,0)),"") | J47: ver anuncio | K47: 46322 | L47: =IF(OR($K47="",D47=""),"",IF(COUNTIFS($B:$B,$B47,$A:$A,$K47,D:D,">=0")=0,"",D47-SUMIFS(D:D,$B:$B,$B47,$A:$A,$K47))) | M47: =IF(OR($K47="",E47=""),"",IF(COUNTIFS($B:$B,$B47,$A:$A,$K47,E:E,">=0")=0,"",E47-SUMIFS(E:E,$B:$B,$B47,$A:$A,$K47))) | N47: =IF(OR($K47="",F47=""),"",IF(COUNTIFS($B:$B,$B47,$A:$A,$K47,F:F,">=0")=0,"",F47-SUMIFS(F:F,$B:$B,$B47,$A:$A,$K47))) | O47: =IF(OR($K47="",G47=""),"",IF(COUNTIFS($B:$B,$B47,$A:$A,$K47,G:G,">=0")=0,"",G47-SUMIFS(G:G,$B:$B,$B47,$A:$A,$K47)))
A48: 46323 | B48: Corsair Vengeance RGB DDR5 32GB (2x16) 5600 | C48: RAM | D48: 459 | E48: 399.99 | H48: =IFERROR(IF(INDEX(Dólar!$B:$B,MATCH(A48,Dólar!$A:$A,0))="","",INDEX(Dólar!$B:$B,MATCH(A48,Dólar!$A:$A,0))),"") | I48: =IFERROR(INDEX(Dólar!$E:$E,MATCH(A48,Dólar!$A:$A,0)),"") | J48: ver anuncio | K48: 46322 | L48: =IF(OR($K48="",D48=""),"",IF(COUNTIFS($B:$B,$B48,$A:$A,$K48,D:D,">=0")=0,"",D48-SUMIFS(D:D,$B:$B,$B48,$A:$A,$K48))) | M48: =IF(OR($K48="",E48=""),"",IF(COUNTIFS($B:$B,$B48,$A:$A,$K48,E:E,">=0")=0,"",E48-SUMIFS(E:E,$B:$B,$B48,$A:$A,$K48))) | N48: =IF(OR($K48="",F48=""),"",IF(COUNTIFS($B:$B,$B48,$A:$A,$K48,F:F,">=0")=0,"",F48-SUMIFS(F:F,$B:$B,$B48,$A:$A,$K48))) | O48: =IF(OR($K48="",G48=""),"",IF(COUNTIFS($B:$B,$B48,$A:$A,$K48,G:G,">=0")=0,"",G48-SUMIFS(G:G,$B:$B,$B48,$A:$A,$K48)))
A49: 46322 | B49: SSD NVMe 2TB | C49: SSD | D49: 185 | E49: 179.99 | H49: =IFERROR(IF(INDEX(Dólar!$B:$B,MATCH(A49,Dólar!$A:$A,0))="","",INDEX(Dólar!$B:$B,MATCH(A49,Dólar!$A:$A,0))),"") | I49: =IFERROR(INDEX(Dólar!$E:$E,MATCH(A49,Dólar!$A:$A,0)),"") | J49: ver anuncio | K49: 46321 | L49: =IF(OR($K49="",D49=""),"",IF(COUNTIFS($B:$B,$B49,$A:$A,$K49,D:D,">=0")=0,"",D49-SUMIFS(D:D,$B:$B,$B49,$A:$A,$K49))) | M49: =IF(OR($K49="",E49=""),"",IF(COUNTIFS($B:$B,$B49,$A:$A,$K49,E:E,">=0")=0,"",E49-SUMIFS(E:E,$B:$B,$B49,$A:$A,$K49))) | N49: =IF(OR($K49="",F49=""),"",IF(COUNTIFS($B:$B,$B49,$A:$A,$K49,F:F,">=0")=0,"",F49-SUMIFS(F:F,$B:$B,$B49,$A:$A,$K49))) | O49: =IF(OR($K49="",G49=""),"",IF(COUNTIFS($B:$B,$B49,$A:$A,$K49,G:G,">=0")=0,"",G49-SUMIFS(G:G,$B:$B,$B49,$A:$A,$K49)))
A50: 46322 | B50: SSD NVMe 1TB | C50: SSD | D50: 114.99 | E50: 89.95 | H50: =IFERROR(IF(INDEX(Dólar!$B:$B,MATCH(A50,Dólar!$A:$A,0))="","",INDEX(Dólar!$B:$B,MATCH(A50,Dólar!$A:$A,0))),"") | I50: =IFERROR(INDEX(Dólar!$E:$E,MATCH(A50,Dólar!$A:$A,0)),"") | J50: ver anuncio | K50: 46321 | L50: =IF(OR($K50="",D50=""),"",IF(COUNTIFS($B:$B,$B50,$A:$A,$K50,D:D,">=0")=0,"",D50-SUMIFS(D:D,$B:$B,$B50,$A:$A,$K50))) | M50: =IF(OR($K50="",E50=""),"",IF(COUNTIFS($B:$B,$B50,$A:$A,$K50,E:E,">=0")=0,"",E50-SUMIFS(E:E,$B:$B,$B50,$A:$A,$K50))) | N50: =IF(OR($K50="",F50=""),"",IF(COUNTIFS($B:$B,$B50,$A:$A,$K50,F:F,">=0")=0,"",F50-SUMIFS(F:F,$B:$B,$B50,$A:$A,$K50))) | O50: =IF(OR($K50="",G50=""),"",IF(COUNTIFS($B:$B,$B50,$A:$A,$K50,G:G,">=0")=0,"",G50-SUMIFS(G:G,$B:$B,$B50,$A:$A,$K50)))
A51: 46322 | B51: Ryzen 9 9950X | C51: CPU | D51: 549.99 | E51: 430 | H51: =IFERROR(IF(INDEX(Dólar!$B:$B,MATCH(A51,Dólar!$A:$A,0))="","",INDEX(Dólar!$B:$B,MATCH(A51,Dólar!$A:$A,0))),"") | I51: =IFERROR(INDEX(Dólar!$E:$E,MATCH(A51,Dólar!$A:$A,0)),"") | J51: ver anuncio | K51: 46321 | L51: =IF(OR($K51="",D51=""),"",IF(COUNTIFS($B:$B,$B51,$A:$A,$K51,D:D,">=0")=0,"",D51-SUMIFS(D:D,$B:$B,$B51,$A:$A,$K51))) | M51: =IF(OR($K51="",E51=""),"",IF(COUNTIFS($B:$B,$B51,$A:$A,$K51,E:E,">=0")=0,"",E51-SUMIFS(E:E,$B:$B,$B51,$A:$A,$K51))) | N51: =IF(OR($K51="",F51=""),"",IF(COUNTIFS($B:$B,$B51,$A:$A,$K51,F:F,">=0")=0,"",F51-SUMIFS(F:F,$B:$B,$B51,$A:$A,$K51))) | O51: =IF(OR($K51="",G51=""),"",IF(COUNTIFS($B:$B,$B51,$A:$A,$K51,G:G,">=0")=0,"",G51-SUMIFS(G:G,$B:$B,$B51,$A:$A,$K51)))
A52: 46322 | B52: Ryzen 7 7800X3D | C52: CPU | D52: 325 | E52: 275 | H52: =IFERROR(IF(INDEX(Dólar!$B:$B,MATCH(A52,Dólar!$A:$A,0))="","",INDEX(Dólar!$B:$B,MATCH(A52,Dólar!$A:$A,0))),"") | I52: =IFERROR(INDEX(Dólar!$E:$E,MATCH(A52,Dólar!$A:$A,0)),"") | J52: ver anuncio | K52: 46321 | L52: =IF(OR($K52="",D52=""),"",IF(COUNTIFS($B:$B,$B52,$A:$A,$K52,D:D,">=0")=0,"",D52-SUMIFS(D:D,$B:$B,$B52,$A:$A,$K52))) | M52: =IF(OR($K52="",E52=""),"",IF(COUNTIFS($B:$B,$B52,$A:$A,$K52,E:E,">=0")=0,"",E52-SUMIFS(E:E,$B:$B,$B52,$A:$A,$K52))) | N52: =IF(OR($K52="",F52=""),"",IF(COUNTIFS($B:$B,$B52,$A:$A,$K52,F:F,">=0")=0,"",F52-SUMIFS(F:F,$B:$B,$B52,$A:$A,$K52))) | O52: =IF(OR($K52="",G52=""),"",IF(COUNTIFS($B:$B,$B52,$A:$A,$K52,G:G,">=0")=0,"",G52-SUMIFS(G:G,$B:$B,$B52,$A:$A,$K52)))
A53: 46322 | B53: Ryzen 7 7700X | C53: CPU | D53: 219 | E53: 189.99 | H53: =IFERROR(IF(INDEX(Dólar!$B:$B,MATCH(A53,Dólar!$A:$A,0))="","",INDEX(Dólar!$B:$B,MATCH(A53,Dólar!$A:$A,0))),"") | I53: =IFERROR(INDEX(Dólar!$E:$E,MATCH(A53,Dólar!$A:$A,0)),"") | J53: ver anuncio | K53: 46321 | L53: =IF(OR($K53="",D53=""),"",IF(COUNTIFS($B:$B,$B53,$A:$A,$K53,D:D,">=0")=0,"",D53-SUMIFS(D:D,$B:$B,$B53,$A:$A,$K53))) | M53: =IF(OR($K53="",E53=""),"",IF(COUNTIFS($B:$B,$B53,$A:$A,$K53,E:E,">=0")=0,"",E53-SUMIFS(E:E,$B:$B,$B53,$A:$A,$K53))) | N53: =IF(OR($K53="",F53=""),"",IF(COUNTIFS($B:$B,$B53,$A:$A,$K53,F:F,">=0")=0,"",F53-SUMIFS(F:F,$B:$B,$B53,$A:$A,$K53))) | O53: =IF(OR($K53="",G53=""),"",IF(COUNTIFS($B:$B,$B53,$A:$A,$K53,G:G,">=0")=0,"",G53-SUMIFS(G:G,$B:$B,$B53,$A:$A,$K53)))
A54: 46322 | B54: Ryzen 7 5700X3D | C54: CPU | E54: 319.99 | H54: =IFERROR(IF(INDEX(Dólar!$B:$B,MATCH(A54,Dólar!$A:$A,0))="","",INDEX(Dólar!$B:$B,MATCH(A54,Dólar!$A:$A,0))),"") | I54: =IFERROR(INDEX(Dólar!$E:$E,MATCH(A54,Dólar!$A:$A,0)),"") | J54: ver anuncio | K54: 46321 | L54: =IF(OR($K54="",D54=""),"",IF(COUNTIFS($B:$B,$B54,$A:$A,$K54,D:D,">=0")=0,"",D54-SUMIFS(D:D,$B:$B,$B54,$A:$A,$K54))) | M54: =IF(OR($K54="",E54=""),"",IF(COUNTIFS($B:$B,$B54,$A:$A,$K54,E:E,">=0")=0,"",E54-SUMIFS(E:E,$B:$B,$B54,$A:$A,$K54))) | N54: =IF(OR($K54="",F54=""),"",IF(COUNTIFS($B:$B,$B54,$A:$A,$K54,F:F,">=0")=0,"",F54-SUMIFS(F:F,$B:$B,$B54,$A:$A,$K54))) | O54: =IF(OR($K54="",G54=""),"",IF(COUNTIFS($B:$B,$B54,$A:$A,$K54,G:G,">=0")=0,"",G54-SUMIFS(G:G,$B:$B,$B54,$A:$A,$K54)))
A55: 46322 | B55: Ryzen 5 7600 | C55: CPU | D55: 146.98 | E55: 119 | H55: =IFERROR(IF(INDEX(Dólar!$B:$B,MATCH(A55,Dólar!$A:$A,0))="","",INDEX(Dólar!$B:$B,MATCH(A55,Dólar!$A:$A,0))),"") | I55: =IFERROR(INDEX(Dólar!$E:$E,MATCH(A55,Dólar!$A:$A,0)),"") | J55: ver anuncio | K55: 46321 | L55: =IF(OR($K55="",D55=""),"",IF(COUNTIFS($B:$B,$B55,$A:$A,$K55,D:D,">=0")=0,"",D55-SUMIFS(D:D,$B:$B,$B55,$A:$A,$K55))) | M55: =IF(OR($K55="",E55=""),"",IF(COUNTIFS($B:$B,$B55,$A:$A,$K55,E:E,">=0")=0,"",E55-SUMIFS(E:E,$B:$B,$B55,$A:$A,$K55))) | N55: =IF(OR($K55="",F55=""),"",IF(COUNTIFS($B:$B,$B55,$A:$A,$K55,F:F,">=0")=0,"",F55-SUMIFS(F:F,$B:$B,$B55,$A:$A,$K55))) | O55: =IF(OR($K55="",G55=""),"",IF(COUNTIFS($B:$B,$B55,$A:$A,$K55,G:G,">=0")=0,"",G55-SUMIFS(G:G,$B:$B,$B55,$A:$A,$K55)))
A56: 46322 | B56: Ryzen 5 7500F | C56: CPU | D56: 135.6 | E56: 129.99 | H56: =IFERROR(IF(INDEX(Dólar!$B:$B,MATCH(A56,Dólar!$A:$A,0))="","",INDEX(Dólar!$B:$B,MATCH(A56,Dólar!$A:$A,0))),"") | I56: =IFERROR(INDEX(Dólar!$E:$E,MATCH(A56,Dólar!$A:$A,0)),"") | J56: ver anuncio | K56: 46321 | L56: =IF(OR($K56="",D56=""),"",IF(COUNTIFS($B:$B,$B56,$A:$A,$K56,D:D,">=0")=0,"",D56-SUMIFS(D:D,$B:$B,$B56,$A:$A,$K56))) | M56: =IF(OR($K56="",E56=""),"",IF(COUNTIFS($B:$B,$B56,$A:$A,$K56,E:E,">=0")=0,"",E56-SUMIFS(E:E,$B:$B,$B56,$A:$A,$K56))) | N56: =IF(OR($K56="",F56=""),"",IF(COUNTIFS($B:$B,$B56,$A:$A,$K56,F:F,">=0")=0,"",F56-SUMIFS(F:F,$B:$B,$B56,$A:$A,$K56))) | O56: =IF(OR($K56="",G56=""),"",IF(COUNTIFS($B:$B,$B56,$A:$A,$K56,G:G,">=0")=0,"",G56-SUMIFS(G:G,$B:$B,$B56,$A:$A,$K56)))
A57: 46322 | B57: Ryzen 5 5600 | C57: CPU | D57: 159.99 | E57: 133.99 | H57: =IFERROR(IF(INDEX(Dólar!$B:$B,MATCH(A57,Dólar!$A:$A,0))="","",INDEX(Dólar!$B:$B,MATCH(A57,Dólar!$A:$A,0))),"") | I57: =IFERROR(INDEX(Dólar!$E:$E,MATCH(A57,Dólar!$A:$A,0)),"") | J57: ver anuncio | K57: 46321 | L57: =IF(OR($K57="",D57=""),"",IF(COUNTIFS($B:$B,$B57,$A:$A,$K57,D:D,">=0")=0,"",D57-SUMIFS(D:D,$B:$B,$B57,$A:$A,$K57))) | M57: =IF(OR($K57="",E57=""),"",IF(COUNTIFS($B:$B,$B57,$A:$A,$K57,E:E,">=0")=0,"",E57-SUMIFS(E:E,$B:$B,$B57,$A:$A,$K57))) | N57: =IF(OR($K57="",F57=""),"",IF(COUNTIFS($B:$B,$B57,$A:$A,$K57,F:F,">=0")=0,"",F57-SUMIFS(F:F,$B:$B,$B57,$A:$A,$K57))) | O57: =IF(OR($K57="",G57=""),"",IF(COUNTIFS($B:$B,$B57,$A:$A,$K57,G:G,">=0")=0,"",G57-SUMIFS(G:G,$B:$B,$B57,$A:$A,$K57)))
A58: 46322 | B58: RAM DDR4 16GB (2x8) 3200 | C58: RAM | D58: 109 | E58: 59.95 | H58: =IFERROR(IF(INDEX(Dólar!$B:$B,MATCH(A58,Dólar!$A:$A,0))="","",INDEX(Dólar!$B:$B,MATCH(A58,Dólar!$A:$A,0))),"") | I58: =IFERROR(INDEX(Dólar!$E:$E,MATCH(A58,Dólar!$A:$A,0)),"") | J58: ver anuncio | K58: 46321 | L58: =IF(OR($K58="",D58=""),"",IF(COUNTIFS($B:$B,$B58,$A:$A,$K58,D:D,">=0")=0,"",D58-SUMIFS(D:D,$B:$B,$B58,$A:$A,$K58))) | M58: =IF(OR($K58="",E58=""),"",IF(COUNTIFS($B:$B,$B58,$A:$A,$K58,E:E,">=0")=0,"",E58-SUMIFS(E:E,$B:$B,$B58,$A:$A,$K58))) | N58: =IF(OR($K58="",F58=""),"",IF(COUNTIFS($B:$B,$B58,$A:$A,$K58,F:F,">=0")=0,"",F58-SUMIFS(F:F,$B:$B,$B58,$A:$A,$K58))) | O58: =IF(OR($K58="",G58=""),"",IF(COUNTIFS($B:$B,$B58,$A:$A,$K58,G:G,">=0")=0,"",G58-SUMIFS(G:G,$B:$B,$B58,$A:$A,$K58)))
A59: 46322 | B59: Intel Core i5-14400F | C59: CPU | D59: 164.49 | E59: 129.99 | H59: =IFERROR(IF(INDEX(Dólar!$B:$B,MATCH(A59,Dólar!$A:$A,0))="","",INDEX(Dólar!$B:$B,MATCH(A59,Dólar!$A:$A,0))),"") | I59: =IFERROR(INDEX(Dólar!$E:$E,MATCH(A59,Dólar!$A:$A,0)),"") | J59: ver anuncio | K59: 46321 | L59: =IF(OR($K59="",D59=""),"",IF(COUNTIFS($B:$B,$B59,$A:$A,$K59,D:D,">=0")=0,"",D59-SUMIFS(D:D,$B:$B,$B59,$A:$A,$K59))) | M59: =IF(OR($K59="",E59=""),"",IF(COUNTIFS($B:$B,$B59,$A:$A,$K59,E:E,">=0")=0,"",E59-SUMIFS(E:E,$B:$B,$B59,$A:$A,$K59))) | N59: =IF(OR($K59="",F59=""),"",IF(COUNTIFS($B:$B,$B59,$A:$A,$K59,F:F,">=0")=0,"",F59-SUMIFS(F:F,$B:$B,$B59,$A:$A,$K59))) | O59: =IF(OR($K59="",G59=""),"",IF(COUNTIFS($B:$B,$B59,$A:$A,$K59,G:G,">=0")=0,"",G59-SUMIFS(G:G,$B:$B,$B59,$A:$A,$K59)))
A60: 46322 | B60: Intel Core i5-13400 | C60: CPU | E60: 150 | H60: =IFERROR(IF(INDEX(Dólar!$B:$B,MATCH(A60,Dólar!$A:$A,0))="","",INDEX(Dólar!$B:$B,MATCH(A60,Dólar!$A:$A,0))),"") | I60: =IFERROR(INDEX(Dólar!$E:$E,MATCH(A60,Dólar!$A:$A,0)),"") | J60: ver anuncio | K60: 46321 | L60: =IF(OR($K60="",D60=""),"",IF(COUNTIFS($B:$B,$B60,$A:$A,$K60,D:D,">=0")=0,"",D60-SUMIFS(D:D,$B:$B,$B60,$A:$A,$K60))) | M60: =IF(OR($K60="",E60=""),"",IF(COUNTIFS($B:$B,$B60,$A:$A,$K60,E:E,">=0")=0,"",E60-SUMIFS(E:E,$B:$B,$B60,$A:$A,$K60))) | N60: =IF(OR($K60="",F60=""),"",IF(COUNTIFS($B:$B,$B60,$A:$A,$K60,F:F,">=0")=0,"",F60-SUMIFS(F:F,$B:$B,$B60,$A:$A,$K60))) | O60: =IF(OR($K60="",G60=""),"",IF(COUNTIFS($B:$B,$B60,$A:$A,$K60,G:G,">=0")=0,"",G60-SUMIFS(G:G,$B:$B,$B60,$A:$A,$K60)))
A61: 46322 | B61: Intel Core i5-12400F | C61: CPU | D61: 140 | E61: 119.89 | H61: =IFERROR(IF(INDEX(Dólar!$B:$B,MATCH(A61,Dólar!$A:$A,0))="","",INDEX(Dólar!$B:$B,MATCH(A61,Dólar!$A:$A,0))),"") | I61: =IFERROR(INDEX(Dólar!$E:$E,MATCH(A61,Dólar!$A:$A,0)),"") | J61: ver anuncio | K61: 46321 | L61: =IF(OR($K61="",D61=""),"",IF(COUNTIFS($B:$B,$B61,$A:$A,$K61,D:D,">=0")=0,"",D61-SUMIFS(D:D,$B:$B,$B61,$A:$A,$K61))) | M61: =IF(OR($K61="",E61=""),"",IF(COUNTIFS($B:$B,$B61,$A:$A,$K61,E:E,">=0")=0,"",E61-SUMIFS(E:E,$B:$B,$B61,$A:$A,$K61))) | N61: =IF(OR($K61="",F61=""),"",IF(COUNTIFS($B:$B,$B61,$A:$A,$K61,F:F,">=0")=0,"",F61-SUMIFS(F:F,$B:$B,$B61,$A:$A,$K61))) | O61: =IF(OR($K61="",G61=""),"",IF(COUNTIFS($B:$B,$B61,$A:$A,$K61,G:G,">=0")=0,"",G61-SUMIFS(G:G,$B:$B,$B61,$A:$A,$K61)))
A62: 46322 | B62: Intel Core Ultra 7 265K | C62: CPU | D62: 259.99 | H62: =IFERROR(IF(INDEX(Dólar!$B:$B,MATCH(A62,Dólar!$A:$A,0))="","",INDEX(Dólar!$B:$B,MATCH(A62,Dólar!$A:$A,0))),"") | I62: =IFERROR(INDEX(Dólar!$E:$E,MATCH(A62,Dólar!$A:$A,0)),"") | J62: ver anuncio | K62: 46321 | L62: =IF(OR($K62="",D62=""),"",IF(COUNTIFS($B:$B,$B62,$A:$A,$K62,D:D,">=0")=0,"",D62-SUMIFS(D:D,$B:$B,$B62,$A:$A,$K62))) | M62: =IF(OR($K62="",E62=""),"",IF(COUNTIFS($B:$B,$B62,$A:$A,$K62,E:E,">=0")=0,"",E62-SUMIFS(E:E,$B:$B,$B62,$A:$A,$K62))) | N62: =IF(OR($K62="",F62=""),"",IF(COUNTIFS($B:$B,$B62,$A:$A,$K62,F:F,">=0")=0,"",F62-SUMIFS(F:F,$B:$B,$B62,$A:$A,$K62))) | O62: =IF(OR($K62="",G62=""),"",IF(COUNTIFS($B:$B,$B62,$A:$A,$K62,G:G,">=0")=0,"",G62-SUMIFS(G:G,$B:$B,$B62,$A:$A,$K62)))
A63: 46322 | B63: Corsair Vengeance RGB DDR5 32GB (2x16) 6000 | C63: RAM | D63: 450 | E63: 399.99 | H63: =IFERROR(IF(INDEX(Dólar!$B:$B,MATCH(A63,Dólar!$A:$A,0))="","",INDEX(Dólar!$B:$B,MATCH(A63,Dólar!$A:$A,0))),"") | I63: =IFERROR(INDEX(Dólar!$E:$E,MATCH(A63,Dólar!$A:$A,0)),"") | J63: ver anuncio | K63: 46321 | L63: =IF(OR($K63="",D63=""),"",IF(COUNTIFS($B:$B,$B63,$A:$A,$K63,D:D,">=0")=0,"",D63-SUMIFS(D:D,$B:$B,$B63,$A:$A,$K63))) | M63: =IF(OR($K63="",E63=""),"",IF(COUNTIFS($B:$B,$B63,$A:$A,$K63,E:E,">=0")=0,"",E63-SUMIFS(E:E,$B:$B,$B63,$A:$A,$K63))) | N63: =IF(OR($K63="",F63=""),"",IF(COUNTIFS($B:$B,$B63,$A:$A,$K63,F:F,">=0")=0,"",F63-SUMIFS(F:F,$B:$B,$B63,$A:$A,$K63))) | O63: =IF(OR($K63="",G63=""),"",IF(COUNTIFS($B:$B,$B63,$A:$A,$K63,G:G,">=0")=0,"",G63-SUMIFS(G:G,$B:$B,$B63,$A:$A,$K63)))
A64: 46322 | B64: Corsair Vengeance RGB DDR5 32GB (2x16) 5600 | C64: RAM | D64: 459 | E64: 399.99 | H64: =IFERROR(IF(INDEX(Dólar!$B:$B,MATCH(A64,Dólar!$A:$A,0))="","",INDEX(Dólar!$B:$B,MATCH(A64,Dólar!$A:$A,0))),"") | I64: =IFERROR(INDEX(Dólar!$E:$E,MATCH(A64,Dólar!$A:$A,0)),"") | J64: ver anuncio | K64: 46321 | L64: =IF(OR($K64="",D64=""),"",IF(COUNTIFS($B:$B,$B64,$A:$A,$K64,D:D,">=0")=0,"",D64-SUMIFS(D:D,$B:$B,$B64,$A:$A,$K64))) | M64: =IF(OR($K64="",E64=""),"",IF(COUNTIFS($B:$B,$B64,$A:$A,$K64,E:E,">=0")=0,"",E64-SUMIFS(E:E,$B:$B,$B64,$A:$A,$K64))) | N64: =IF(OR($K64="",F64=""),"",IF(COUNTIFS($B:$B,$B64,$A:$A,$K64,F:F,">=0")=0,"",F64-SUMIFS(F:F,$B:$B,$B64,$A:$A,$K64))) | O64: =IF(OR($K64="",G64=""),"",IF(COUNTIFS($B:$B,$B64,$A:$A,$K64,G:G,">=0")=0,"",G64-SUMIFS(G:G,$B:$B,$B64,$A:$A,$K64)))
A65: 46321 | B65: SSD NVMe 2TB | C65: SSD | D65: 185 | E65: 154.99 | H65: =IFERROR(IF(INDEX(Dólar!$B:$B,MATCH(A65,Dólar!$A:$A,0))="","",INDEX(Dólar!$B:$B,MATCH(A65,Dólar!$A:$A,0))),"") | I65: =IFERROR(INDEX(Dólar!$E:$E,MATCH(A65,Dólar!$A:$A,0)),"") | J65: ver anuncio | K65: 46320 | L65: =IF(OR($K65="",D65=""),"",IF(COUNTIFS($B:$B,$B65,$A:$A,$K65,D:D,">=0")=0,"",D65-SUMIFS(D:D,$B:$B,$B65,$A:$A,$K65))) | M65: =IF(OR($K65="",E65=""),"",IF(COUNTIFS($B:$B,$B65,$A:$A,$K65,E:E,">=0")=0,"",E65-SUMIFS(E:E,$B:$B,$B65,$A:$A,$K65))) | N65: =IF(OR($K65="",F65=""),"",IF(COUNTIFS($B:$B,$B65,$A:$A,$K65,F:F,">=0")=0,"",F65-SUMIFS(F:F,$B:$B,$B65,$A:$A,$K65))) | O65: =IF(OR($K65="",G65=""),"",IF(COUNTIFS($B:$B,$B65,$A:$A,$K65,G:G,">=0")=0,"",G65-SUMIFS(G:G,$B:$B,$B65,$A:$A,$K65)))
A66: 46321 | B66: SSD NVMe 1TB | C66: SSD | D66: 114.99 | E66: 85 | F66: 1850 | G66: 2000 | H66: =IFERROR(IF(INDEX(Dólar!$B:$B,MATCH(A66,Dólar!$A:$A,0))="","",INDEX(Dólar!$B:$B,MATCH(A66,Dólar!$A:$A,0))),"") | I66: =IFERROR(INDEX(Dólar!$E:$E,MATCH(A66,Dólar!$A:$A,0)),"") | J66: ver anuncio | K66: 46320 | L66: =IF(OR($K66="",D66=""),"",IF(COUNTIFS($B:$B,$B66,$A:$A,$K66,D:D,">=0")=0,"",D66-SUMIFS(D:D,$B:$B,$B66,$A:$A,$K66))) | M66: =IF(OR($K66="",E66=""),"",IF(COUNTIFS($B:$B,$B66,$A:$A,$K66,E:E,">=0")=0,"",E66-SUMIFS(E:E,$B:$B,$B66,$A:$A,$K66))) | N66: =IF(OR($K66="",F66=""),"",IF(COUNTIFS($B:$B,$B66,$A:$A,$K66,F:F,">=0")=0,"",F66-SUMIFS(F:F,$B:$B,$B66,$A:$A,$K66))) | O66: =IF(OR($K66="",G66=""),"",IF(COUNTIFS($B:$B,$B66,$A:$A,$K66,G:G,">=0")=0,"",G66-SUMIFS(G:G,$B:$B,$B66,$A:$A,$K66)))
A67: 46321 | B67: Ryzen 9 9950X | C67: CPU | D67: 549.99 | E67: 454.99 | H67: =IFERROR(IF(INDEX(Dólar!$B:$B,MATCH(A67,Dólar!$A:$A,0))="","",INDEX(Dólar!$B:$B,MATCH(A67,Dólar!$A:$A,0))),"") | I67: =IFERROR(INDEX(Dólar!$E:$E,MATCH(A67,Dólar!$A:$A,0)),"") | J67: ver anuncio | K67: 46320 | L67: =IF(OR($K67="",D67=""),"",IF(COUNTIFS($B:$B,$B67,$A:$A,$K67,D:D,">=0")=0,"",D67-SUMIFS(D:D,$B:$B,$B67,$A:$A,$K67))) | M67: =IF(OR($K67="",E67=""),"",IF(COUNTIFS($B:$B,$B67,$A:$A,$K67,E:E,">=0")=0,"",E67-SUMIFS(E:E,$B:$B,$B67,$A:$A,$K67))) | N67: =IF(OR($K67="",F67=""),"",IF(COUNTIFS($B:$B,$B67,$A:$A,$K67,F:F,">=0")=0,"",F67-SUMIFS(F:F,$B:$B,$B67,$A:$A,$K67))) | O67: =IF(OR($K67="",G67=""),"",IF(COUNTIFS($B:$B,$B67,$A:$A,$K67,G:G,">=0")=0,"",G67-SUMIFS(G:G,$B:$B,$B67,$A:$A,$K67)))
A68: 46321 | B68: Ryzen 7 7800X3D | C68: CPU | D68: 329 | E68: 269.99 | F68: 4800 | H68: =IFERROR(IF(INDEX(Dólar!$B:$B,MATCH(A68,Dólar!$A:$A,0))="","",INDEX(Dólar!$B:$B,MATCH(A68,Dólar!$A:$A,0))),"") | I68: =IFERROR(INDEX(Dólar!$E:$E,MATCH(A68,Dólar!$A:$A,0)),"") | J68: ver anuncio | K68: 46320 | L68: =IF(OR($K68="",D68=""),"",IF(COUNTIFS($B:$B,$B68,$A:$A,$K68,D:D,">=0")=0,"",D68-SUMIFS(D:D,$B:$B,$B68,$A:$A,$K68))) | M68: =IF(OR($K68="",E68=""),"",IF(COUNTIFS($B:$B,$B68,$A:$A,$K68,E:E,">=0")=0,"",E68-SUMIFS(E:E,$B:$B,$B68,$A:$A,$K68))) | N68: =IF(OR($K68="",F68=""),"",IF(COUNTIFS($B:$B,$B68,$A:$A,$K68,F:F,">=0")=0,"",F68-SUMIFS(F:F,$B:$B,$B68,$A:$A,$K68))) | O68: =IF(OR($K68="",G68=""),"",IF(COUNTIFS($B:$B,$B68,$A:$A,$K68,G:G,">=0")=0,"",G68-SUMIFS(G:G,$B:$B,$B68,$A:$A,$K68)))
A69: 46321 | B69: Ryzen 7 7700X | C69: CPU | D69: 219 | E69: 189.99 | H69: =IFERROR(IF(INDEX(Dólar!$B:$B,MATCH(A69,Dólar!$A:$A,0))="","",INDEX(Dólar!$B:$B,MATCH(A69,Dólar!$A:$A,0))),"") | I69: =IFERROR(INDEX(Dólar!$E:$E,MATCH(A69,Dólar!$A:$A,0)),"") | J69: ver anuncio | K69: 46320 | L69: =IF(OR($K69="",D69=""),"",IF(COUNTIFS($B:$B,$B69,$A:$A,$K69,D:D,">=0")=0,"",D69-SUMIFS(D:D,$B:$B,$B69,$A:$A,$K69))) | M69: =IF(OR($K69="",E69=""),"",IF(COUNTIFS($B:$B,$B69,$A:$A,$K69,E:E,">=0")=0,"",E69-SUMIFS(E:E,$B:$B,$B69,$A:$A,$K69))) | N69: =IF(OR($K69="",F69=""),"",IF(COUNTIFS($B:$B,$B69,$A:$A,$K69,F:F,">=0")=0,"",F69-SUMIFS(F:F,$B:$B,$B69,$A:$A,$K69))) | O69: =IF(OR($K69="",G69=""),"",IF(COUNTIFS($B:$B,$B69,$A:$A,$K69,G:G,">=0")=0,"",G69-SUMIFS(G:G,$B:$B,$B69,$A:$A,$K69)))
A70: 46321 | B70: Ryzen 7 5700X3D | C70: CPU | E70: 336 | H70: =IFERROR(IF(INDEX(Dólar!$B:$B,MATCH(A70,Dólar!$A:$A,0))="","",INDEX(Dólar!$B:$B,MATCH(A70,Dólar!$A:$A,0))),"") | I70: =IFERROR(INDEX(Dólar!$E:$E,MATCH(A70,Dólar!$A:$A,0)),"") | J70: ver anuncio | K70: 46320 | L70: =IF(OR($K70="",D70=""),"",IF(COUNTIFS($B:$B,$B70,$A:$A,$K70,D:D,">=0")=0,"",D70-SUMIFS(D:D,$B:$B,$B70,$A:$A,$K70))) | M70: =IF(OR($K70="",E70=""),"",IF(COUNTIFS($B:$B,$B70,$A:$A,$K70,E:E,">=0")=0,"",E70-SUMIFS(E:E,$B:$B,$B70,$A:$A,$K70))) | N70: =IF(OR($K70="",F70=""),"",IF(COUNTIFS($B:$B,$B70,$A:$A,$K70,F:F,">=0")=0,"",F70-SUMIFS(F:F,$B:$B,$B70,$A:$A,$K70))) | O70: =IF(OR($K70="",G70=""),"",IF(COUNTIFS($B:$B,$B70,$A:$A,$K70,G:G,">=0")=0,"",G70-SUMIFS(G:G,$B:$B,$B70,$A:$A,$K70)))
A71: 46321 | B71: Ryzen 5 7600 | C71: CPU | D71: 199.99 | E71: 119 | H71: =IFERROR(IF(INDEX(Dólar!$B:$B,MATCH(A71,Dólar!$A:$A,0))="","",INDEX(Dólar!$B:$B,MATCH(A71,Dólar!$A:$A,0))),"") | I71: =IFERROR(INDEX(Dólar!$E:$E,MATCH(A71,Dólar!$A:$A,0)),"") | J71: ver anuncio | K71: 46320 | L71: =IF(OR($K71="",D71=""),"",IF(COUNTIFS($B:$B,$B71,$A:$A,$K71,D:D,">=0")=0,"",D71-SUMIFS(D:D,$B:$B,$B71,$A:$A,$K71))) | M71: =IF(OR($K71="",E71=""),"",IF(COUNTIFS($B:$B,$B71,$A:$A,$K71,E:E,">=0")=0,"",E71-SUMIFS(E:E,$B:$B,$B71,$A:$A,$K71))) | N71: =IF(OR($K71="",F71=""),"",IF(COUNTIFS($B:$B,$B71,$A:$A,$K71,F:F,">=0")=0,"",F71-SUMIFS(F:F,$B:$B,$B71,$A:$A,$K71))) | O71: =IF(OR($K71="",G71=""),"",IF(COUNTIFS($B:$B,$B71,$A:$A,$K71,G:G,">=0")=0,"",G71-SUMIFS(G:G,$B:$B,$B71,$A:$A,$K71)))
A72: 46321 | B72: Ryzen 5 7500F | C72: CPU | D72: 135.6 | E72: 129.99 | H72: =IFERROR(IF(INDEX(Dólar!$B:$B,MATCH(A72,Dólar!$A:$A,0))="","",INDEX(Dólar!$B:$B,MATCH(A72,Dólar!$A:$A,0))),"") | I72: =IFERROR(INDEX(Dólar!$E:$E,MATCH(A72,Dólar!$A:$A,0)),"") | J72: ver anuncio | K72: 46320 | L72: =IF(OR($K72="",D72=""),"",IF(COUNTIFS($B:$B,$B72,$A:$A,$K72,D:D,">=0")=0,"",D72-SUMIFS(D:D,$B:$B,$B72,$A:$A,$K72))) | M72: =IF(OR($K72="",E72=""),"",IF(COUNTIFS($B:$B,$B72,$A:$A,$K72,E:E,">=0")=0,"",E72-SUMIFS(E:E,$B:$B,$B72,$A:$A,$K72))) | N72: =IF(OR($K72="",F72=""),"",IF(COUNTIFS($B:$B,$B72,$A:$A,$K72,F:F,">=0")=0,"",F72-SUMIFS(F:F,$B:$B,$B72,$A:$A,$K72))) | O72: =IF(OR($K72="",G72=""),"",IF(COUNTIFS($B:$B,$B72,$A:$A,$K72,G:G,">=0")=0,"",G72-SUMIFS(G:G,$B:$B,$B72,$A:$A,$K72)))
A73: 46321 | B73: Ryzen 5 5600 | C73: CPU | D73: 138.9 | E73: 135.99 | H73: =IFERROR(IF(INDEX(Dólar!$B:$B,MATCH(A73,Dólar!$A:$A,0))="","",INDEX(Dólar!$B:$B,MATCH(A73,Dólar!$A:$A,0))),"") | I73: =IFERROR(INDEX(Dólar!$E:$E,MATCH(A73,Dólar!$A:$A,0)),"") | J73: ver anuncio | K73: 46320 | L73: =IF(OR($K73="",D73=""),"",IF(COUNTIFS($B:$B,$B73,$A:$A,$K73,D:D,">=0")=0,"",D73-SUMIFS(D:D,$B:$B,$B73,$A:$A,$K73))) | M73: =IF(OR($K73="",E73=""),"",IF(COUNTIFS($B:$B,$B73,$A:$A,$K73,E:E,">=0")=0,"",E73-SUMIFS(E:E,$B:$B,$B73,$A:$A,$K73))) | N73: =IF(OR($K73="",F73=""),"",IF(COUNTIFS($B:$B,$B73,$A:$A,$K73,F:F,">=0")=0,"",F73-SUMIFS(F:F,$B:$B,$B73,$A:$A,$K73))) | O73: =IF(OR($K73="",G73=""),"",IF(COUNTIFS($B:$B,$B73,$A:$A,$K73,G:G,">=0")=0,"",G73-SUMIFS(G:G,$B:$B,$B73,$A:$A,$K73)))
A74: 46321 | B74: RAM DDR4 16GB (2x8) 3200 | C74: RAM | D74: 109 | E74: 59.99 | H74: =IFERROR(IF(INDEX(Dólar!$B:$B,MATCH(A74,Dólar!$A:$A,0))="","",INDEX(Dólar!$B:$B,MATCH(A74,Dólar!$A:$A,0))),"") | I74: =IFERROR(INDEX(Dólar!$E:$E,MATCH(A74,Dólar!$A:$A,0)),"") | J74: ver anuncio | K74: 46320 | L74: =IF(OR($K74="",D74=""),"",IF(COUNTIFS($B:$B,$B74,$A:$A,$K74,D:D,">=0")=0,"",D74-SUMIFS(D:D,$B:$B,$B74,$A:$A,$K74))) | M74: =IF(OR($K74="",E74=""),"",IF(COUNTIFS($B:$B,$B74,$A:$A,$K74,E:E,">=0")=0,"",E74-SUMIFS(E:E,$B:$B,$B74,$A:$A,$K74))) | N74: =IF(OR($K74="",F74=""),"",IF(COUNTIFS($B:$B,$B74,$A:$A,$K74,F:F,">=0")=0,"",F74-SUMIFS(F:F,$B:$B,$B74,$A:$A,$K74))) | O74: =IF(OR($K74="",G74=""),"",IF(COUNTIFS($B:$B,$B74,$A:$A,$K74,G:G,">=0")=0,"",G74-SUMIFS(G:G,$B:$B,$B74,$A:$A,$K74)))
A75: 46321 | B75: Intel Core i5-14400F | C75: CPU | D75: 164.49 | E75: 129.99 | H75: =IFERROR(IF(INDEX(Dólar!$B:$B,MATCH(A75,Dólar!$A:$A,0))="","",INDEX(Dólar!$B:$B,MATCH(A75,Dólar!$A:$A,0))),"") | I75: =IFERROR(INDEX(Dólar!$E:$E,MATCH(A75,Dólar!$A:$A,0)),"") | J75: ver anuncio | K75: 46320 | L75: =IF(OR($K75="",D75=""),"",IF(COUNTIFS($B:$B,$B75,$A:$A,$K75,D:D,">=0")=0,"",D75-SUMIFS(D:D,$B:$B,$B75,$A:$A,$K75))) | M75: =IF(OR($K75="",E75=""),"",IF(COUNTIFS($B:$B,$B75,$A:$A,$K75,E:E,">=0")=0,"",E75-SUMIFS(E:E,$B:$B,$B75,$A:$A,$K75))) | N75: =IF(OR($K75="",F75=""),"",IF(COUNTIFS($B:$B,$B75,$A:$A,$K75,F:F,">=0")=0,"",F75-SUMIFS(F:F,$B:$B,$B75,$A:$A,$K75))) | O75: =IF(OR($K75="",G75=""),"",IF(COUNTIFS($B:$B,$B75,$A:$A,$K75,G:G,">=0")=0,"",G75-SUMIFS(G:G,$B:$B,$B75,$A:$A,$K75)))
A76: 46321 | B76: Intel Core i5-13400 | C76: CPU | E76: 150 | H76: =IFERROR(IF(INDEX(Dólar!$B:$B,MATCH(A76,Dólar!$A:$A,0))="","",INDEX(Dólar!$B:$B,MATCH(A76,Dólar!$A:$A,0))),"") | I76: =IFERROR(INDEX(Dólar!$E:$E,MATCH(A76,Dólar!$A:$A,0)),"") | J76: ver anuncio | K76: 46320 | L76: =IF(OR($K76="",D76=""),"",IF(COUNTIFS($B:$B,$B76,$A:$A,$K76,D:D,">=0")=0,"",D76-SUMIFS(D:D,$B:$B,$B76,$A:$A,$K76))) | M76: =IF(OR($K76="",E76=""),"",IF(COUNTIFS($B:$B,$B76,$A:$A,$K76,E:E,">=0")=0,"",E76-SUMIFS(E:E,$B:$B,$B76,$A:$A,$K76))) | N76: =IF(OR($K76="",F76=""),"",IF(COUNTIFS($B:$B,$B76,$A:$A,$K76,F:F,">=0")=0,"",F76-SUMIFS(F:F,$B:$B,$B76,$A:$A,$K76))) | O76: =IF(OR($K76="",G76=""),"",IF(COUNTIFS($B:$B,$B76,$A:$A,$K76,G:G,">=0")=0,"",G76-SUMIFS(G:G,$B:$B,$B76,$A:$A,$K76)))
A77: 46321 | B77: Intel Core i5-12400F | C77: CPU | D77: 140 | E77: 119.99 | H77: =IFERROR(IF(INDEX(Dólar!$B:$B,MATCH(A77,Dólar!$A:$A,0))="","",INDEX(Dólar!$B:$B,MATCH(A77,Dólar!$A:$A,0))),"") | I77: =IFERROR(INDEX(Dólar!$E:$E,MATCH(A77,Dólar!$A:$A,0)),"") | J77: ver anuncio | K77: 46320 | L77: =IF(OR($K77="",D77=""),"",IF(COUNTIFS($B:$B,$B77,$A:$A,$K77,D:D,">=0")=0,"",D77-SUMIFS(D:D,$B:$B,$B77,$A:$A,$K77))) | M77: =IF(OR($K77="",E77=""),"",IF(COUNTIFS($B:$B,$B77,$A:$A,$K77,E:E,">=0")=0,"",E77-SUMIFS(E:E,$B:$B,$B77,$A:$A,$K77))) | N77: =IF(OR($K77="",F77=""),"",IF(COUNTIFS($B:$B,$B77,$A:$A,$K77,F:F,">=0")=0,"",F77-SUMIFS(F:F,$B:$B,$B77,$A:$A,$K77))) | O77: =IF(OR($K77="",G77=""),"",IF(COUNTIFS($B:$B,$B77,$A:$A,$K77,G:G,">=0")=0,"",G77-SUMIFS(G:G,$B:$B,$B77,$A:$A,$K77)))
A78: 46321 | B78: Intel Core Ultra 7 265K | C78: CPU | D78: 259.99 | H78: =IFERROR(IF(INDEX(Dólar!$B:$B,MATCH(A78,Dólar!$A:$A,0))="","",INDEX(Dólar!$B:$B,MATCH(A78,Dólar!$A:$A,0))),"") | I78: =IFERROR(INDEX(Dólar!$E:$E,MATCH(A78,Dólar!$A:$A,0)),"") | J78: ver anuncio | K78: 46320 | L78: =IF(OR($K78="",D78=""),"",IF(COUNTIFS($B:$B,$B78,$A:$A,$K78,D:D,">=0")=0,"",D78-SUMIFS(D:D,$B:$B,$B78,$A:$A,$K78))) | M78: =IF(OR($K78="",E78=""),"",IF(COUNTIFS($B:$B,$B78,$A:$A,$K78,E:E,">=0")=0,"",E78-SUMIFS(E:E,$B:$B,$B78,$A:$A,$K78))) | N78: =IF(OR($K78="",F78=""),"",IF(COUNTIFS($B:$B,$B78,$A:$A,$K78,F:F,">=0")=0,"",F78-SUMIFS(F:F,$B:$B,$B78,$A:$A,$K78))) | O78: =IF(OR($K78="",G78=""),"",IF(COUNTIFS($B:$B,$B78,$A:$A,$K78,G:G,">=0")=0,"",G78-SUMIFS(G:G,$B:$B,$B78,$A:$A,$K78)))
A79: 46321 | B79: Corsair Vengeance RGB DDR5 32GB (2x16) 6000 | C79: RAM | D79: 450 | E79: 399.99 | H79: =IFERROR(IF(INDEX(Dólar!$B:$B,MATCH(A79,Dólar!$A:$A,0))="","",INDEX(Dólar!$B:$B,MATCH(A79,Dólar!$A:$A,0))),"") | I79: =IFERROR(INDEX(Dólar!$E:$E,MATCH(A79,Dólar!$A:$A,0)),"") | J79: ver anuncio | K79: 46320 | L79: =IF(OR($K79="",D79=""),"",IF(COUNTIFS($B:$B,$B79,$A:$A,$K79,D:D,">=0")=0,"",D79-SUMIFS(D:D,$B:$B,$B79,$A:$A,$K79))) | M79: =IF(OR($K79="",E79=""),"",IF(COUNTIFS($B:$B,$B79,$A:$A,$K79,E:E,">=0")=0,"",E79-SUMIFS(E:E,$B:$B,$B79,$A:$A,$K79))) | N79: =IF(OR($K79="",F79=""),"",IF(COUNTIFS($B:$B,$B79,$A:$A,$K79,F:F,">=0")=0,"",F79-SUMIFS(F:F,$B:$B,$B79,$A:$A,$K79))) | O79: =IF(OR($K79="",G79=""),"",IF(COUNTIFS($B:$B,$B79,$A:$A,$K79,G:G,">=0")=0,"",G79-SUMIFS(G:G,$B:$B,$B79,$A:$A,$K79)))
A80: 46321 | B80: Corsair Vengeance RGB DDR5 32GB (2x16) 5600 | C80: RAM | D80: 459 | E80: 389.99 | H80: =IFERROR(IF(INDEX(Dólar!$B:$B,MATCH(A80,Dólar!$A:$A,0))="","",INDEX(Dólar!$B:$B,MATCH(A80,Dólar!$A:$A,0))),"") | I80: =IFERROR(INDEX(Dólar!$E:$E,MATCH(A80,Dólar!$A:$A,0)),"") | J80: ver anuncio | K80: 46320 | L80: =IF(OR($K80="",D80=""),"",IF(COUNTIFS($B:$B,$B80,$A:$A,$K80,D:D,">=0")=0,"",D80-SUMIFS(D:D,$B:$B,$B80,$A:$A,$K80))) | M80: =IF(OR($K80="",E80=""),"",IF(COUNTIFS($B:$B,$B80,$A:$A,$K80,E:E,">=0")=0,"",E80-SUMIFS(E:E,$B:$B,$B80,$A:$A,$K80))) | N80: =IF(OR($K80="",F80=""),"",IF(COUNTIFS($B:$B,$B80,$A:$A,$K80,F:F,">=0")=0,"",F80-SUMIFS(F:F,$B:$B,$B80,$A:$A,$K80))) | O80: =IF(OR($K80="",G80=""),"",IF(COUNTIFS($B:$B,$B80,$A:$A,$K80,G:G,">=0")=0,"",G80-SUMIFS(G:G,$B:$B,$B80,$A:$A,$K80)))
A81: 46320 | B81: SSD NVMe 2TB | C81: SSD | D81: 185 | E81: 169.99 | H81: =IFERROR(IF(INDEX(Dólar!$B:$B,MATCH(A81,Dólar!$A:$A,0))="","",INDEX(Dólar!$B:$B,MATCH(A81,Dólar!$A:$A,0))),"") | I81: =IFERROR(INDEX(Dólar!$E:$E,MATCH(A81,Dólar!$A:$A,0)),"") | J81: ver anuncio | K81: 46319 | L81: =IF(OR($K81="",D81=""),"",IF(COUNTIFS($B:$B,$B81,$A:$A,$K81,D:D,">=0")=0,"",D81-SUMIFS(D:D,$B:$B,$B81,$A:$A,$K81))) | M81: =IF(OR($K81="",E81=""),"",IF(COUNTIFS($B:$B,$B81,$A:$A,$K81,E:E,">=0")=0,"",E81-SUMIFS(E:E,$B:$B,$B81,$A:$A,$K81))) | N81: =IF(OR($K81="",F81=""),"",IF(COUNTIFS($B:$B,$B81,$A:$A,$K81,F:F,">=0")=0,"",F81-SUMIFS(F:F,$B:$B,$B81,$A:$A,$K81))) | O81: =IF(OR($K81="",G81=""),"",IF(COUNTIFS($B:$B,$B81,$A:$A,$K81,G:G,">=0")=0,"",G81-SUMIFS(G:G,$B:$B,$B81,$A:$A,$K81)))
A82: 46320 | B82: SSD NVMe 1TB | C82: SSD | D82: 114.99 | E82: 85 | H82: =IFERROR(IF(INDEX(Dólar!$B:$B,MATCH(A82,Dólar!$A:$A,0))="","",INDEX(Dólar!$B:$B,MATCH(A82,Dólar!$A:$A,0))),"") | I82: =IFERROR(INDEX(Dólar!$E:$E,MATCH(A82,Dólar!$A:$A,0)),"") | J82: ver anuncio | K82: 46319 | L82: =IF(OR($K82="",D82=""),"",IF(COUNTIFS($B:$B,$B82,$A:$A,$K82,D:D,">=0")=0,"",D82-SUMIFS(D:D,$B:$B,$B82,$A:$A,$K82))) | M82: =IF(OR($K82="",E82=""),"",IF(COUNTIFS($B:$B,$B82,$A:$A,$K82,E:E,">=0")=0,"",E82-SUMIFS(E:E,$B:$B,$B82,$A:$A,$K82))) | N82: =IF(OR($K82="",F82=""),"",IF(COUNTIFS($B:$B,$B82,$A:$A,$K82,F:F,">=0")=0,"",F82-SUMIFS(F:F,$B:$B,$B82,$A:$A,$K82))) | O82: =IF(OR($K82="",G82=""),"",IF(COUNTIFS($B:$B,$B82,$A:$A,$K82,G:G,">=0")=0,"",G82-SUMIFS(G:G,$B:$B,$B82,$A:$A,$K82)))
A83: 46320 | B83: Ryzen 9 9950X | C83: CPU | D83: 549.99 | E83: 454.99 | H83: =IFERROR(IF(INDEX(Dólar!$B:$B,MATCH(A83,Dólar!$A:$A,0))="","",INDEX(Dólar!$B:$B,MATCH(A83,Dólar!$A:$A,0))),"") | I83: =IFERROR(INDEX(Dólar!$E:$E,MATCH(A83,Dólar!$A:$A,0)),"") | J83: ver anuncio | K83: 46319 | L83: =IF(OR($K83="",D83=""),"",IF(COUNTIFS($B:$B,$B83,$A:$A,$K83,D:D,">=0")=0,"",D83-SUMIFS(D:D,$B:$B,$B83,$A:$A,$K83))) | M83: =IF(OR($K83="",E83=""),"",IF(COUNTIFS($B:$B,$B83,$A:$A,$K83,E:E,">=0")=0,"",E83-SUMIFS(E:E,$B:$B,$B83,$A:$A,$K83))) | N83: =IF(OR($K83="",F83=""),"",IF(COUNTIFS($B:$B,$B83,$A:$A,$K83,F:F,">=0")=0,"",F83-SUMIFS(F:F,$B:$B,$B83,$A:$A,$K83))) | O83: =IF(OR($K83="",G83=""),"",IF(COUNTIFS($B:$B,$B83,$A:$A,$K83,G:G,">=0")=0,"",G83-SUMIFS(G:G,$B:$B,$B83,$A:$A,$K83)))
A84: 46320 | B84: Ryzen 7 7800X3D | C84: CPU | D84: 329 | E84: 275 | H84: =IFERROR(IF(INDEX(Dólar!$B:$B,MATCH(A84,Dólar!$A:$A,0))="","",INDEX(Dólar!$B:$B,MATCH(A84,Dólar!$A:$A,0))),"") | I84: =IFERROR(INDEX(Dólar!$E:$E,MATCH(A84,Dólar!$A:$A,0)),"") | J84: ver anuncio | K84: 46319 | L84: =IF(OR($K84="",D84=""),"",IF(COUNTIFS($B:$B,$B84,$A:$A,$K84,D:D,">=0")=0,"",D84-SUMIFS(D:D,$B:$B,$B84,$A:$A,$K84))) | M84: =IF(OR($K84="",E84=""),"",IF(COUNTIFS($B:$B,$B84,$A:$A,$K84,E:E,">=0")=0,"",E84-SUMIFS(E:E,$B:$B,$B84,$A:$A,$K84))) | N84: =IF(OR($K84="",F84=""),"",IF(COUNTIFS($B:$B,$B84,$A:$A,$K84,F:F,">=0")=0,"",F84-SUMIFS(F:F,$B:$B,$B84,$A:$A,$K84))) | O84: =IF(OR($K84="",G84=""),"",IF(COUNTIFS($B:$B,$B84,$A:$A,$K84,G:G,">=0")=0,"",G84-SUMIFS(G:G,$B:$B,$B84,$A:$A,$K84)))
A85: 46320 | B85: Ryzen 7 7700X | C85: CPU | D85: 219 | E85: 149 | H85: =IFERROR(IF(INDEX(Dólar!$B:$B,MATCH(A85,Dólar!$A:$A,0))="","",INDEX(Dólar!$B:$B,MATCH(A85,Dólar!$A:$A,0))),"") | I85: =IFERROR(INDEX(Dólar!$E:$E,MATCH(A85,Dólar!$A:$A,0)),"") | J85: ver anuncio | K85: 46319 | L85: =IF(OR($K85="",D85=""),"",IF(COUNTIFS($B:$B,$B85,$A:$A,$K85,D:D,">=0")=0,"",D85-SUMIFS(D:D,$B:$B,$B85,$A:$A,$K85))) | M85: =IF(OR($K85="",E85=""),"",IF(COUNTIFS($B:$B,$B85,$A:$A,$K85,E:E,">=0")=0,"",E85-SUMIFS(E:E,$B:$B,$B85,$A:$A,$K85))) | N85: =IF(OR($K85="",F85=""),"",IF(COUNTIFS($B:$B,$B85,$A:$A,$K85,F:F,">=0")=0,"",F85-SUMIFS(F:F,$B:$B,$B85,$A:$A,$K85))) | O85: =IF(OR($K85="",G85=""),"",IF(COUNTIFS($B:$B,$B85,$A:$A,$K85,G:G,">=0")=0,"",G85-SUMIFS(G:G,$B:$B,$B85,$A:$A,$K85)))
A86: 46320 | B86: Ryzen 7 5700X3D | C86: CPU | E86: 299.5 | H86: =IFERROR(IF(INDEX(Dólar!$B:$B,MATCH(A86,Dólar!$A:$A,0))="","",INDEX(Dólar!$B:$B,MATCH(A86,Dólar!$A:$A,0))),"") | I86: =IFERROR(INDEX(Dólar!$E:$E,MATCH(A86,Dólar!$A:$A,0)),"") | J86: ver anuncio | K86: 46319 | L86: =IF(OR($K86="",D86=""),"",IF(COUNTIFS($B:$B,$B86,$A:$A,$K86,D:D,">=0")=0,"",D86-SUMIFS(D:D,$B:$B,$B86,$A:$A,$K86))) | M86: =IF(OR($K86="",E86=""),"",IF(COUNTIFS($B:$B,$B86,$A:$A,$K86,E:E,">=0")=0,"",E86-SUMIFS(E:E,$B:$B,$B86,$A:$A,$K86))) | N86: =IF(OR($K86="",F86=""),"",IF(COUNTIFS($B:$B,$B86,$A:$A,$K86,F:F,">=0")=0,"",F86-SUMIFS(F:F,$B:$B,$B86,$A:$A,$K86))) | O86: =IF(OR($K86="",G86=""),"",IF(COUNTIFS($B:$B,$B86,$A:$A,$K86,G:G,">=0")=0,"",G86-SUMIFS(G:G,$B:$B,$B86,$A:$A,$K86)))
A87: 46320 | B87: Ryzen 5 7600 | C87: CPU | D87: 199.99 | E87: 119 | H87: =IFERROR(IF(INDEX(Dólar!$B:$B,MATCH(A87,Dólar!$A:$A,0))="","",INDEX(Dólar!$B:$B,MATCH(A87,Dólar!$A:$A,0))),"") | I87: =IFERROR(INDEX(Dólar!$E:$E,MATCH(A87,Dólar!$A:$A,0)),"") | J87: ver anuncio | K87: 46319 | L87: =IF(OR($K87="",D87=""),"",IF(COUNTIFS($B:$B,$B87,$A:$A,$K87,D:D,">=0")=0,"",D87-SUMIFS(D:D,$B:$B,$B87,$A:$A,$K87))) | M87: =IF(OR($K87="",E87=""),"",IF(COUNTIFS($B:$B,$B87,$A:$A,$K87,E:E,">=0")=0,"",E87-SUMIFS(E:E,$B:$B,$B87,$A:$A,$K87))) | N87: =IF(OR($K87="",F87=""),"",IF(COUNTIFS($B:$B,$B87,$A:$A,$K87,F:F,">=0")=0,"",F87-SUMIFS(F:F,$B:$B,$B87,$A:$A,$K87))) | O87: =IF(OR($K87="",G87=""),"",IF(COUNTIFS($B:$B,$B87,$A:$A,$K87,G:G,">=0")=0,"",G87-SUMIFS(G:G,$B:$B,$B87,$A:$A,$K87)))
A88: 46320 | B88: Ryzen 5 7500F | C88: CPU | D88: 135.99 | E88: 129.99 | H88: =IFERROR(IF(INDEX(Dólar!$B:$B,MATCH(A88,Dólar!$A:$A,0))="","",INDEX(Dólar!$B:$B,MATCH(A88,Dólar!$A:$A,0))),"") | I88: =IFERROR(INDEX(Dólar!$E:$E,MATCH(A88,Dólar!$A:$A,0)),"") | J88: ver anuncio | K88: 46319 | L88: =IF(OR($K88="",D88=""),"",IF(COUNTIFS($B:$B,$B88,$A:$A,$K88,D:D,">=0")=0,"",D88-SUMIFS(D:D,$B:$B,$B88,$A:$A,$K88))) | M88: =IF(OR($K88="",E88=""),"",IF(COUNTIFS($B:$B,$B88,$A:$A,$K88,E:E,">=0")=0,"",E88-SUMIFS(E:E,$B:$B,$B88,$A:$A,$K88))) | N88: =IF(OR($K88="",F88=""),"",IF(COUNTIFS($B:$B,$B88,$A:$A,$K88,F:F,">=0")=0,"",F88-SUMIFS(F:F,$B:$B,$B88,$A:$A,$K88))) | O88: =IF(OR($K88="",G88=""),"",IF(COUNTIFS($B:$B,$B88,$A:$A,$K88,G:G,">=0")=0,"",G88-SUMIFS(G:G,$B:$B,$B88,$A:$A,$K88)))
A89: 46320 | B89: Ryzen 5 5600 | C89: CPU | D89: 135.98 | E89: 120 | H89: =IFERROR(IF(INDEX(Dólar!$B:$B,MATCH(A89,Dólar!$A:$A,0))="","",INDEX(Dólar!$B:$B,MATCH(A89,Dólar!$A:$A,0))),"") | I89: =IFERROR(INDEX(Dólar!$E:$E,MATCH(A89,Dólar!$A:$A,0)),"") | J89: ver anuncio | K89: 46319 | L89: =IF(OR($K89="",D89=""),"",IF(COUNTIFS($B:$B,$B89,$A:$A,$K89,D:D,">=0")=0,"",D89-SUMIFS(D:D,$B:$B,$B89,$A:$A,$K89))) | M89: =IF(OR($K89="",E89=""),"",IF(COUNTIFS($B:$B,$B89,$A:$A,$K89,E:E,">=0")=0,"",E89-SUMIFS(E:E,$B:$B,$B89,$A:$A,$K89))) | N89: =IF(OR($K89="",F89=""),"",IF(COUNTIFS($B:$B,$B89,$A:$A,$K89,F:F,">=0")=0,"",F89-SUMIFS(F:F,$B:$B,$B89,$A:$A,$K89))) | O89: =IF(OR($K89="",G89=""),"",IF(COUNTIFS($B:$B,$B89,$A:$A,$K89,G:G,">=0")=0,"",G89-SUMIFS(G:G,$B:$B,$B89,$A:$A,$K89)))
A90: 46320 | B90: RAM DDR4 16GB (2x8) 3200 | C90: RAM | D90: 109 | E90: 59.99 | H90: =IFERROR(IF(INDEX(Dólar!$B:$B,MATCH(A90,Dólar!$A:$A,0))="","",INDEX(Dólar!$B:$B,MATCH(A90,Dólar!$A:$A,0))),"") | I90: =IFERROR(INDEX(Dólar!$E:$E,MATCH(A90,Dólar!$A:$A,0)),"") | J90: ver anuncio | K90: 46319 | L90: =IF(OR($K90="",D90=""),"",IF(COUNTIFS($B:$B,$B90,$A:$A,$K90,D:D,">=0")=0,"",D90-SUMIFS(D:D,$B:$B,$B90,$A:$A,$K90))) | M90: =IF(OR($K90="",E90=""),"",IF(COUNTIFS($B:$B,$B90,$A:$A,$K90,E:E,">=0")=0,"",E90-SUMIFS(E:E,$B:$B,$B90,$A:$A,$K90))) | N90: =IF(OR($K90="",F90=""),"",IF(COUNTIFS($B:$B,$B90,$A:$A,$K90,F:F,">=0")=0,"",F90-SUMIFS(F:F,$B:$B,$B90,$A:$A,$K90))) | O90: =IF(OR($K90="",G90=""),"",IF(COUNTIFS($B:$B,$B90,$A:$A,$K90,G:G,">=0")=0,"",G90-SUMIFS(G:G,$B:$B,$B90,$A:$A,$K90)))
A91: 46320 | B91: Intel Core i5-14400F | C91: CPU | D91: 164.49 | E91: 129.99 | H91: =IFERROR(IF(INDEX(Dólar!$B:$B,MATCH(A91,Dólar!$A:$A,0))="","",INDEX(Dólar!$B:$B,MATCH(A91,Dólar!$A:$A,0))),"") | I91: =IFERROR(INDEX(Dólar!$E:$E,MATCH(A91,Dólar!$A:$A,0)),"") | J91: ver anuncio | K91: 46319 | L91: =IF(OR($K91="",D91=""),"",IF(COUNTIFS($B:$B,$B91,$A:$A,$K91,D:D,">=0")=0,"",D91-SUMIFS(D:D,$B:$B,$B91,$A:$A,$K91))) | M91: =IF(OR($K91="",E91=""),"",IF(COUNTIFS($B:$B,$B91,$A:$A,$K91,E:E,">=0")=0,"",E91-SUMIFS(E:E,$B:$B,$B91,$A:$A,$K91))) | N91: =IF(OR($K91="",F91=""),"",IF(COUNTIFS($B:$B,$B91,$A:$A,$K91,F:F,">=0")=0,"",F91-SUMIFS(F:F,$B:$B,$B91,$A:$A,$K91))) | O91: =IF(OR($K91="",G91=""),"",IF(COUNTIFS($B:$B,$B91,$A:$A,$K91,G:G,">=0")=0,"",G91-SUMIFS(G:G,$B:$B,$B91,$A:$A,$K91)))
A92: 46320 | B92: Intel Core i5-13400 | C92: CPU | E92: 149.95 | H92: =IFERROR(IF(INDEX(Dólar!$B:$B,MATCH(A92,Dólar!$A:$A,0))="","",INDEX(Dólar!$B:$B,MATCH(A92,Dólar!$A:$A,0))),"") | I92: =IFERROR(INDEX(Dólar!$E:$E,MATCH(A92,Dólar!$A:$A,0)),"") | J92: ver anuncio | K92: 46319 | L92: =IF(OR($K92="",D92=""),"",IF(COUNTIFS($B:$B,$B92,$A:$A,$K92,D:D,">=0")=0,"",D92-SUMIFS(D:D,$B:$B,$B92,$A:$A,$K92))) | M92: =IF(OR($K92="",E92=""),"",IF(COUNTIFS($B:$B,$B92,$A:$A,$K92,E:E,">=0")=0,"",E92-SUMIFS(E:E,$B:$B,$B92,$A:$A,$K92))) | N92: =IF(OR($K92="",F92=""),"",IF(COUNTIFS($B:$B,$B92,$A:$A,$K92,F:F,">=0")=0,"",F92-SUMIFS(F:F,$B:$B,$B92,$A:$A,$K92))) | O92: =IF(OR($K92="",G92=""),"",IF(COUNTIFS($B:$B,$B92,$A:$A,$K92,G:G,">=0")=0,"",G92-SUMIFS(G:G,$B:$B,$B92,$A:$A,$K92)))
A93: 46320 | B93: Intel Core i5-12400F | C93: CPU | D93: 145 | E93: 112 | H93: =IFERROR(IF(INDEX(Dólar!$B:$B,MATCH(A93,Dólar!$A:$A,0))="","",INDEX(Dólar!$B:$B,MATCH(A93,Dólar!$A:$A,0))),"") | I93: =IFERROR(INDEX(Dólar!$E:$E,MATCH(A93,Dólar!$A:$A,0)),"") | J93: ver anuncio | K93: 46319 | L93: =IF(OR($K93="",D93=""),"",IF(COUNTIFS($B:$B,$B93,$A:$A,$K93,D:D,">=0")=0,"",D93-SUMIFS(D:D,$B:$B,$B93,$A:$A,$K93))) | M93: =IF(OR($K93="",E93=""),"",IF(COUNTIFS($B:$B,$B93,$A:$A,$K93,E:E,">=0")=0,"",E93-SUMIFS(E:E,$B:$B,$B93,$A:$A,$K93))) | N93: =IF(OR($K93="",F93=""),"",IF(COUNTIFS($B:$B,$B93,$A:$A,$K93,F:F,">=0")=0,"",F93-SUMIFS(F:F,$B:$B,$B93,$A:$A,$K93))) | O93: =IF(OR($K93="",G93=""),"",IF(COUNTIFS($B:$B,$B93,$A:$A,$K93,G:G,">=0")=0,"",G93-SUMIFS(G:G,$B:$B,$B93,$A:$A,$K93)))
A94: 46320 | B94: Intel Core Ultra 7 265K | C94: CPU | D94: 259.99 | E94: 238 | H94: =IFERROR(IF(INDEX(Dólar!$B:$B,MATCH(A94,Dólar!$A:$A,0))="","",INDEX(Dólar!$B:$B,MATCH(A94,Dólar!$A:$A,0))),"") | I94: =IFERROR(INDEX(Dólar!$E:$E,MATCH(A94,Dólar!$A:$A,0)),"") | J94: ver anuncio | K94: 46319 | L94: =IF(OR($K94="",D94=""),"",IF(COUNTIFS($B:$B,$B94,$A:$A,$K94,D:D,">=0")=0,"",D94-SUMIFS(D:D,$B:$B,$B94,$A:$A,$K94))) | M94: =IF(OR($K94="",E94=""),"",IF(COUNTIFS($B:$B,$B94,$A:$A,$K94,E:E,">=0")=0,"",E94-SUMIFS(E:E,$B:$B,$B94,$A:$A,$K94))) | N94: =IF(OR($K94="",F94=""),"",IF(COUNTIFS($B:$B,$B94,$A:$A,$K94,F:F,">=0")=0,"",F94-SUMIFS(F:F,$B:$B,$B94,$A:$A,$K94))) | O94: =IF(OR($K94="",G94=""),"",IF(COUNTIFS($B:$B,$B94,$A:$A,$K94,G:G,">=0")=0,"",G94-SUMIFS(G:G,$B:$B,$B94,$A:$A,$K94)))
A95: 46320 | B95: Corsair Vengeance RGB DDR5 32GB (2x16) 6000 | C95: RAM | D95: 450 | E95: 389.99 | H95: =IFERROR(IF(INDEX(Dólar!$B:$B,MATCH(A95,Dólar!$A:$A,0))="","",INDEX(Dólar!$B:$B,MATCH(A95,Dólar!$A:$A,0))),"") | I95: =IFERROR(INDEX(Dólar!$E:$E,MATCH(A95,Dólar!$A:$A,0)),"") | J95: ver anuncio | K95: 46319 | L95: =IF(OR($K95="",D95=""),"",IF(COUNTIFS($B:$B,$B95,$A:$A,$K95,D:D,">=0")=0,"",D95-SUMIFS(D:D,$B:$B,$B95,$A:$A,$K95))) | M95: =IF(OR($K95="",E95=""),"",IF(COUNTIFS($B:$B,$B95,$A:$A,$K95,E:E,">=0")=0,"",E95-SUMIFS(E:E,$B:$B,$B95,$A:$A,$K95))) | N95: =IF(OR($K95="",F95=""),"",IF(COUNTIFS($B:$B,$B95,$A:$A,$K95,F:F,">=0")=0,"",F95-SUMIFS(F:F,$B:$B,$B95,$A:$A,$K95))) | O95: =IF(OR($K95="",G95=""),"",IF(COUNTIFS($B:$B,$B95,$A:$A,$K95,G:G,">=0")=0,"",G95-SUMIFS(G:G,$B:$B,$B95,$A:$A,$K95)))
A96: 46320 | B96: Corsair Vengeance RGB DDR5 32GB (2x16) 5600 | C96: RAM | D96: 459 | E96: 389.99 | H96: =IFERROR(IF(INDEX(Dólar!$B:$B,MATCH(A96,Dólar!$A:$A,0))="","",INDEX(Dólar!$B:$B,MATCH(A96,Dólar!$A:$A,0))),"") | I96: =IFERROR(INDEX(Dólar!$E:$E,MATCH(A96,Dólar!$A:$A,0)),"") | J96: ver anuncio | K96: 46319 | L96: =IF(OR($K96="",D96=""),"",IF(COUNTIFS($B:$B,$B96,$A:$A,$K96,D:D,">=0")=0,"",D96-SUMIFS(D:D,$B:$B,$B96,$A:$A,$K96))) | M96: =IF(OR($K96="",E96=""),"",IF(COUNTIFS($B:$B,$B96,$A:$A,$K96,E:E,">=0")=0,"",E96-SUMIFS(E:E,$B:$B,$B96,$A:$A,$K96))) | N96: =IF(OR($K96="",F96=""),"",IF(COUNTIFS($B:$B,$B96,$A:$A,$K96,F:F,">=0")=0,"",F96-SUMIFS(F:F,$B:$B,$B96,$A:$A,$K96))) | O96: =IF(OR($K96="",G96=""),"",IF(COUNTIFS($B:$B,$B96,$A:$A,$K96,G:G,">=0")=0,"",G96-SUMIFS(G:G,$B:$B,$B96,$A:$A,$K96)))
A97: 46319 | B97: SSD NVMe 2TB | C97: SSD | D97: 185 | E97: 179.99 | H97: =IFERROR(IF(INDEX(Dólar!$B:$B,MATCH(A97,Dólar!$A:$A,0))="","",INDEX(Dólar!$B:$B,MATCH(A97,Dólar!$A:$A,0))),"") | I97: =IFERROR(INDEX(Dólar!$E:$E,MATCH(A97,Dólar!$A:$A,0)),"") | J97: ver anuncio | K97: 46318 | L97: =IF(OR($K97="",D97=""),"",IF(COUNTIFS($B:$B,$B97,$A:$A,$K97,D:D,">=0")=0,"",D97-SUMIFS(D:D,$B:$B,$B97,$A:$A,$K97))) | M97: =IF(OR($K97="",E97=""),"",IF(COUNTIFS($B:$B,$B97,$A:$A,$K97,E:E,">=0")=0,"",E97-SUMIFS(E:E,$B:$B,$B97,$A:$A,$K97))) | N97: =IF(OR($K97="",F97=""),"",IF(COUNTIFS($B:$B,$B97,$A:$A,$K97,F:F,">=0")=0,"",F97-SUMIFS(F:F,$B:$B,$B97,$A:$A,$K97))) | O97: =IF(OR($K97="",G97=""),"",IF(COUNTIFS($B:$B,$B97,$A:$A,$K97,G:G,">=0")=0,"",G97-SUMIFS(G:G,$B:$B,$B97,$A:$A,$K97)))
A98: 46319 | B98: SSD NVMe 1TB | C98: SSD | D98: 114.99 | E98: 85 | H98: =IFERROR(IF(INDEX(Dólar!$B:$B,MATCH(A98,Dólar!$A:$A,0))="","",INDEX(Dólar!$B:$B,MATCH(A98,Dólar!$A:$A,0))),"") | I98: =IFERROR(INDEX(Dólar!$E:$E,MATCH(A98,Dólar!$A:$A,0)),"") | J98: ver anuncio | K98: 46318 | L98: =IF(OR($K98="",D98=""),"",IF(COUNTIFS($B:$B,$B98,$A:$A,$K98,D:D,">=0")=0,"",D98-SUMIFS(D:D,$B:$B,$B98,$A:$A,$K98))) | M98: =IF(OR($K98="",E98=""),"",IF(COUNTIFS($B:$B,$B98,$A:$A,$K98,E:E,">=0")=0,"",E98-SUMIFS(E:E,$B:$B,$B98,$A:$A,$K98))) | N98: =IF(OR($K98="",F98=""),"",IF(COUNTIFS($B:$B,$B98,$A:$A,$K98,F:F,">=0")=0,"",F98-SUMIFS(F:F,$B:$B,$B98,$A:$A,$K98))) | O98: =IF(OR($K98="",G98=""),"",IF(COUNTIFS($B:$B,$B98,$A:$A,$K98,G:G,">=0")=0,"",G98-SUMIFS(G:G,$B:$B,$B98,$A:$A,$K98)))
A99: 46319 | B99: Ryzen 9 9950X | C99: CPU | D99: 549.99 | E99: 454.99 | H99: =IFERROR(IF(INDEX(Dólar!$B:$B,MATCH(A99,Dólar!$A:$A,0))="","",INDEX(Dólar!$B:$B,MATCH(A99,Dólar!$A:$A,0))),"") | I99: =IFERROR(INDEX(Dólar!$E:$E,MATCH(A99,Dólar!$A:$A,0)),"") | J99: ver anuncio | K99: 46318 | L99: =IF(OR($K99="",D99=""),"",IF(COUNTIFS($B:$B,$B99,$A:$A,$K99,D:D,">=0")=0,"",D99-SUMIFS(D:D,$B:$B,$B99,$A:$A,$K99))) | M99: =IF(OR($K99="",E99=""),"",IF(COUNTIFS($B:$B,$B99,$A:$A,$K99,E:E,">=0")=0,"",E99-SUMIFS(E:E,$B:$B,$B99,$A:$A,$K99))) | N99: =IF(OR($K99="",F99=""),"",IF(COUNTIFS($B:$B,$B99,$A:$A,$K99,F:F,">=0")=0,"",F99-SUMIFS(F:F,$B:$B,$B99,$A:$A,$K99))) | O99: =IF(OR($K99="",G99=""),"",IF(COUNTIFS($B:$B,$B99,$A:$A,$K99,G:G,">=0")=0,"",G99-SUMIFS(G:G,$B:$B,$B99,$A:$A,$K99)))
A100: 46319 | B100: Ryzen 7 7800X3D | C100: CPU | D100: 329 | E100: 275 | H100: =IFERROR(IF(INDEX(Dólar!$B:$B,MATCH(A100,Dólar!$A:$A,0))="","",INDEX(Dólar!$B:$B,MATCH(A100,Dólar!$A:$A,0))),"") | I100: =IFERROR(INDEX(Dólar!$E:$E,MATCH(A100,Dólar!$A:$A,0)),"") | J100: ver anuncio | K100: 46318 | L100: =IF(OR($K100="",D100=""),"",IF(COUNTIFS($B:$B,$B100,$A:$A,$K100,D:D,">=0")=0,"",D100-SUMIFS(D:D,$B:$B,$B100,$A:$A,$K100))) | M100: =IF(OR($K100="",E100=""),"",IF(COUNTIFS($B:$B,$B100,$A:$A,$K100,E:E,">=0")=0,"",E100-SUMIFS(E:E,$B:$B,$B100,$A:$A,$K100))) | N100: =IF(OR($K100="",F100=""),"",IF(COUNTIFS($B:$B,$B100,$A:$A,$K100,F:F,">=0")=0,"",F100-SUMIFS(F:F,$B:$B,$B100,$A:$A,$K100))) | O100: =IF(OR($K100="",G100=""),"",IF(COUNTIFS($B:$B,$B100,$A:$A,$K100,G:G,">=0")=0,"",G100-SUMIFS(G:G,$B:$B,$B100,$A:$A,$K100)))
...

Sheet Supuestos
A1: Supuestos del cálculo (celdas azules: se pueden cambiar)
A3: Unidades por pedido | B3: 2
A4: Courier B: USD por kg | B4: 28
A5: Courier B: mínimo kg | B5: 1
A6: Courier B: salto kg | B6: 0.5
A7: Caja exterior + relleno, g | B7: 300
A8: Courier A: USD por producto | B8: 10
A9: Courier A: sales tax | B9: 0.07
A10: Aduana boliviana extra (incluida en los couriers) | B10: 0
A11: Dólar para cálculos, Bs/USD | B11: =INDEX(Dólar!$F:$F,MATCH(MAX(Dólar!$A:$A),Dólar!$A:$A,0))
A12: Umbral 'Conviene' | B12: 0.15
A13: Umbral 'Justo' | B13: 0.05
A15: Fuente de los supuestos: CLAUDE.md (couriers del usuario). Dólar: hoja Dólar (BCB y paralelo P2P).

Sheet Dólar
A1: Fecha | B1: Oficial BCB | C1: Paralelo compra | D1: Paralelo venta | E1: Paralelo promedio | F1: Usado en cálculos | G1: Fuente
A2: 46305 | B2: 11.73 | C2: 11.86 | D2: 11.91 | E2: =IF(COUNT(C2:D2)=2,AVERAGE(C2:D2),"") | F2: 11.9 | G2: referencia del usuario (CLAUDE.md)
A3: 46306 | E3: =IF(COUNT(C3:D3)=2,AVERAGE(C3:D3),"") | F3: 11.9 | G3: sin cotización del día: se usó la referencia del 10/10 (estimado)
A4: 46307 | B4: 11.73 | C4: 11.86 | D4: 11.83 | E4: =IF(COUNT(C4:D4)=2,AVERAGE(C4:D4),"") | F4: 11.85 | G4: BCB oficial del 12/10 (Red Uno); paralelo dolarbolivia.net 12/10 08:50 (promedio de 8 plataformas P2P); usado = promedio del paralelo
A5: 46308 | B5: 11.73 | C5: 11.85 | D5: 11.88 | E5: =IF(COUNT(C5:D5)=2,AVERAGE(C5:D5),"") | F5: 11.87 | G5: BCB oficial 11.73; paralelo dolarbolivia.net 13/10 (compra 11.85 / venta 11.88); usado = promedio del paralelo
A6: 46309 | B6: 11.7 | C6: 11.84 | D6: 11.88 | E6: =IF(COUNT(C6:D6)=2,AVERAGE(C6:D6),"") | F6: 11.86 | G6: BCB oficial 11.70; paralelo dolarbolivia.net 14/10 (compra 11.84 / venta 11.88; la página es inconsistente entre compra y venta); usado = promedio del paralelo
A7: 46310 | B7: 11.7 | C7: 11.86 | D7: 11.83 | E7: =IF(COUNT(C7:D7)=2,AVERAGE(C7:D7),"") | F7: 11.85 | G7: BCB oficial 11.70; paralelo dolarbolivia.net 15/10 (compra 11.86 / venta 11.83; la página es inconsistente entre compra y venta); usado = promedio del paralelo
A8: 46311 | B8: 11.68 | C8: 11.83 | D8: 11.79 | E8: =IF(COUNT(C8:D8)=2,AVERAGE(C8:D8),"") | F8: 11.81 | G8: BCB oficial 11.68; paralelo dolarbolivia.net 16/10 (compra 11.83 / venta 11.79; la página es inconsistente entre compra y venta); usado = promedio del paralelo
A9: 46312 | B9: 11.68 | C9: 11.83 | D9: 11.79 | E9: =IF(COUNT(C9:D9)=2,AVERAGE(C9:D9),"") | F9: 11.81 | G9: BCB oficial 11.68; paralelo dolarbolivia.net 17/10 (compra 11.83 / venta 11.79; la página es inconsistente entre compra y venta); usado = promedio del paralelo
A10: 46313 | B10: 11.69 | C10: 11.85 | D10: 11.81 | E10: =IF(COUNT(C10:D10)=2,AVERAGE(C10:D10),"") | F10: 11.83 | G10: BCB oficial 11.69; paralelo dolarbolivia.net 18/10 (compra 11.85 / venta 11.81; la página es inconsistente entre compra y venta); usado = promedio del paralelo
A11: 46314 | B11: 11.69 | C11: 11.83 | D11: 11.8 | E11: =IF(COUNT(C11:D11)=2,AVERAGE(C11:D11),"") | F11: 11.82 | G11: BCB oficial 11.69; paralelo dolarbolivia.net 19/10 11:55 (compra 11.83 / venta 11.80); usado = promedio del paralelo
A12: 46315 | B12: 11.7 | C12: 11.84 | D12: 11.82 | E12: =IF(COUNT(C12:D12)=2,AVERAGE(C12:D12),"") | F12: 11.83 | G12: BCB oficial 11.70 (bcb.gob.bo); paralelo dolarbolivia.net 20/10 07:55 (compra 11.84 / venta 11.82); usado = promedio del paralelo
A13: 46316 | B13: 11.7 | C13: 11.91 | D13: 11.9 | E13: =IF(COUNT(C13:D13)=2,AVERAGE(C13:D13),"") | F13: 11.91 | G13: BCB oficial 11.70 (dolarbolivia.net 21/10 11:54); paralelo dolarbolivia.net 21/10 (compra 11.91 / venta 11.90); usado = promedio del paralelo
A14: 46317 | B14: 11.73 | C14: 11.91 | D14: 11.88 | E14: =IF(COUNT(C14:D14)=2,AVERAGE(C14:D14),"") | F14: 11.9 | G14: BCB oficial 11.73 (dolarbolivia.net 22/10 07:55); paralelo dolarbolivia.net 22/10 (compra 11.91 / venta 11.88); usado = promedio del paralelo
A15: 46318 | B15: 11.75 | C15: 11.94 | D15: 11.92 | E15: =IF(COUNT(C15:D15)=2,AVERAGE(C15:D15),"") | F15: 11.93 | G15: BCB oficial 11.75 (dolarbolivia.net 23/10 07:54); paralelo dolarbolivia.net 23/10 (compra 11.94 / venta 11.92); usado = promedio del paralelo
... A21: 46324 | B21: 12.02 | C21: 12.16 | D21: 12.14 | E21: =IF(COUNT(C21:D21)=2,AVERAGE(C21:D21),"") | F21: 12.2 | G21: Oficial y paralelo del 28/10 (dolarbolivia.net; no hallé el de hoy); USDT CriptoYa (Binance P2P) 29/10 07:56 BOT, usado = USDT para comprar; CriptoYa USDT, nube 29/10; USDT CriptoYa (Binance P2P) 07:57 BOT (comprar 12.2 / vender 12.16), usado = USDT para comprar
A22: 46325 | E22: =IF(COUNT(C22:D22)=2,AVERAGE(C22:D22),"") | F22: 11.98 | G22: USDT CriptoYa (Binance P2P) 10:36 BOT (comprar 11.98 / vender 11.95), usado = USDT para comprar

Sheet Movimientos
A1: Fecha | B1: Origen | C1: Producto | D1: Condición / vendedor | E1: Precio | F1: Moneda | G1: Detalle | H1: Link
A2: 46307 | B2: eBay | C2: Ryzen 5 5600 | D2: nuevo | E2: 159.99 | F2: USD | G2: eBay vía Chrome, vendedor en EE.UU. (PC de la casa); envío gratis | H2: ver
A3: 46307 | B3: eBay | C3: Ryzen 5 5600 | D3: usado | E3: 124.68 | F3: USD | G3: eBay vía Chrome, vendedor en EE.UU. (PC de la casa) | H3: ver
A4: 46307 | B4: eBay | C4: Ryzen 7 5700X3D | D4: usado | E4: 305.79 | F4: USD | G4: eBay vía Chrome, vendedor en EE.UU. (PC de la casa); no hay nuevos de vendedores de EE.UU. | H4: ver
A5: 46307 | B5: eBay | C5: Ryzen 5 7600 | D5: nuevo | E5: 137.04 | F5: USD | G5: eBay vía Chrome, vendedor en EE.UU. (PC de la casa); tray/OEM; en caja USD 240,53 | H5: ver
A6: 46307 | B6: eBay | C6: Ryzen 5 7600 | D6: usado | E6: 120.99 | F6: USD | G6: eBay vía Chrome, vendedor en EE.UU. (PC de la casa) | H6: ver
A7: 46307 | B7: eBay | C7: Ryzen 7 7800X3D | D7: nuevo | E7: 320 | F7: USD | G7: eBay vía Chrome, vendedor en EE.UU. (PC de la casa); envío gratis | H7: ver
A8: 46307 | B8: eBay | C8: Ryzen 7 7800X3D | D8: usado | E8: 282.52 | F8: USD | G8: eBay vía Chrome, vendedor en EE.UU. (PC de la casa) | H8: ver
A9: 46307 | B9: eBay | C9: Ryzen 9 9950X | D9: nuevo | E9: 512.1 | F9: USD | G9: eBay vía Chrome, vendedor en EE.UU. (PC de la casa) | H9: ver
A10: 46307 | B10: eBay | C10: Ryzen 9 9950X | D10: usado | E10: 410 | F10: USD | G10: eBay vía Chrome, vendedor en EE.UU. (PC de la casa) | H10: ver
A11: 46307 | B11: eBay | C11: Intel Core i5-12400F | D11: nuevo | E11: 159.95 | F11: USD | G11: eBay vía Chrome, vendedor en EE.UU. (PC de la casa); en caja, envío gratis | H11: ver
A12: 46307 | B12: eBay | C12: Intel Core i5-12400F | D12: usado | E12: 124.99 | F12: USD | G12: eBay vía Chrome, vendedor en EE.UU. (PC de la casa) | H12: ver
A13: 46307 | B13: eBay | C13: Intel Core i5-13400 | D13: nuevo | E13: 259.78 | F13: USD | G13: eBay vía Chrome, vendedor en EE.UU. (PC de la casa); tray/OEM; pocos anuncios | H13: ver
... A594: 46307 | B594: Tienda | C594: Intel Core Ultra 7 265K | D594: Viadata Computadoras (WhatsApp) | E594: 5200 | F594: Bs | G594: nuevo en caja (es el 265KF, sin gráficos integrados; solo referencia; no cuenta) | H594: ver
A595: 46308 | B595: Tienda | C595: Ryzen 7 7800X3D | D595: OverCity (WhatsApp) | E595: 5500 | F595: Bs | G595: nuevo OEM (solo el chip)
A596: 46308 | B596: Tienda | C596: Intel Core i5-14400F | D596: OverCity (WhatsApp) | E596: 2460 | F596: Bs | G596: nuevo OEM
A597: 46308 | B597: Tienda | C597: Intel Core i5-14400F | D597: Soft Computers (WhatsApp) | E597: 2500 | F597: Bs | G597: nuevo OEM
A598: 46308 | B598: Tienda | C598: Corsair Vengeance RGB DDR5 32GB (2x16) 6000 | D598: OverCity (WhatsApp) | E598: 6840 | F598: Bs | G598: nuevo (XPG Lancer RGB 32GB 2x16 6000 CL30: otra marca; no cuenta; Corsair agotada; garantía 3 meses)
A599: 46308 | B599: Marketplace | C599: Ryzen 7 7800X3D | D599: Marketplace Cochabamba (particular/vendedor; Messenger) | E599: 4800 | F599: Bs | G599: nuevo sellado de fábrica, confirmado por el vendedor (último en stock; precio ya rebajado) | H599: ver
A600: 46308 | B600: Tienda | C600: Ryzen 7 7800X3D | D600: OverCity (WhatsApp) | E600: 5350 | F600: Bs | G600: nuevo en caja sellada (box; el OEM está a Bs 5.500; el i5-14400F Bs 2.460 es su precio mínimo)
A601: 46309 | B601: Marketplace | C601: Corsair Vengeance RGB DDR5 32GB (2x16) 5600 | D601: Marketplace Cochabamba | E601: 7400 | F601: Bs | G601: no indicado (Kingston Fury Beast DDR5 32GB 5600: otra marca; solo referencia; no cuenta) | H601: ver
A602: 46309 | B602: Tienda | C602: Intel Core i5-14400F | D602: Geek Store Bolivia (web) | E602: 2953 | F602: Bs | G602: disponible (web; es el i5-14400 con gráficos, no el F; precio USD 249 en la web, a Bs 11,86; solo referencia; no cuenta) | H602: ver
A603: 46309 | B603: Tienda | C603: Intel Core i9-14900K | D603: Crazy Store (WhatsApp) | E603: 6013 | F603: Bs | G603: nuevo (no está en vigilar.csv; USD 499 o Bs 6.013, rebaja ofrecida hasta Bs 5.700; solo referencia; no cuenta)
A604: 46310 | B604: Tienda | C604: Ryzen 7 7800X3D | D604: SMART CUBE (WhatsApp) | E604: 5890 | F604: Bs | G604: nuevo sellado, facturado; llevando 2 rebajan Bs 50 c/u (Bs 5.840)
A605: 46310 | B605: Tienda | C605: Intel Core i5-14400F | D605: SMART CUBE (WhatsApp) | E605: 3080 | F605: Bs | G605: nuevo sellado; llevando 2 rebajan Bs 50 c/u (Bs 3.030)
A606: 46310 | B606: Tienda | C606: RAM DDR5 16GB 6000 (Apacer NOX) | D606: SMART CUBE (WhatsApp) | E606: 3650 | F606: Bs | G606: nuevo (Apacer NOX DDR5 16GB 6000: otra marca y capacidad; solo referencia; no cuenta)
A607: 46310 | B607: Tienda | C607: RAM DDR5 16GB | D607: PC Factor (WhatsApp) | E607: 3792 | F607: Bs | G607: nuevo (USD 320 c/u a Bs 11,85; marca y velocidad por confirmar; solo referencia; no cuenta)
A608: 46310 | B608: Tienda | C608: Ryzen 5 7600 | D608: OverCity (WhatsApp) | E608: 2800 | F608: Bs | G608: OEM
A609: 46310 | B609: Tienda | C609: Intel Core i5-12400F | D609: T&T Todo en Tecnología (WhatsApp) | E609: 2260 | F609: Bs | G609: OEM con cooler Intel; Bs 20 menos c/u llevando 2
A610: 46310 | B610: Tienda | C610: Intel Core i5-14400F | D610: T&T Todo en Tecnología (WhatsApp) | E610: 2750 | F610: Bs | G610: OEM con cooler Intel; Bs 20 menos c/u llevando 2
A611: 46310 | B611: Tienda | C611: Ryzen 7 7700X | D611: Geek Store Bolivia (WhatsApp) | E611: 3480 | F611: Bs | G611: sin confirmar si es sellado (se preguntó)
A612: 46310 | B612: Tienda | C612: Kingston Fury DDR5 16GB (1 módulo) | D612: Geek Store Bolivia (WhatsApp) | E612: 2900 | F612: Bs | G612: otra marca; velocidad por confirmar (no es la Corsair 32GB 2x16)
A613: 46310 | B613: Tienda | C613: SSD NVMe 1TB | D613: Shopping PC (catálogo PDF) | E613: 1754 | F613: Bs | G613: nuevo (Kingston NV3 1TB; lista mayorista USD 148 del 12/10, sin factura; 146 en stock)
A614: 46310 | B614: Tienda | C614: Intel Core i5-14400F | D614: Shopping PC (catálogo PDF) | E614: 2785 | F614: Bs | G614: nuevo en caja (es el i5-14400 BOX con gráficos, no el F; lista mayorista USD 235, sin factura; solo referencia; no cuenta)
... A617: 46311 | B617: Tienda | C617: Intel Core i5-14400F | D617: Soft Computers (WhatsApp) | E617: 2500 | F617: Bs | G617: nuevo OEM; mismo precio por unidad llevando 2
A618: 46311 | B618: Marketplace | C618: SSD NVMe 1TB | D618: Marketplace Cochabamba | E618: 1730 | F618: Bs | G618: nuevo (M.2 1TB, marca no indicada; publicado hace 2 días) | H618: ver
A619: 46311 | B619: Tienda | C619: Intel Core i5-14400F | D619: Cyrex Store (web) | E619: 2384 | F619: Bs | G619: nuevo OEM (web: USD 202 a la tasa de la tienda, 11,80; hay otra publicación del mismo a USD 215) | H619: ver
A620: 46311 | B620: Tienda | C620: Ryzen 7 7800X3D | D620: Cyrex Store (web) | E620: 5664 | F620: Bs | G620: nuevo BOX (web: USD 480 a 11,80) | H620: ver
A621: 46311 | B621: Tienda | C621: Intel Core i5-13400 | D621: Cyrex Store (web) | E621: 2218 | F621: Bs | G621: nuevo OEM (web: es el i5-13400F, sin gráficos; USD 188 a 11,80; solo referencia; no cuenta) | H621: ver
A622: 46311 | B622: Tienda | C622: Ryzen 5 7600 | D622: Punto Tecnológico (WhatsApp) | E622: 2850 | F622: Bs | G622: nuevo OEM, garantía 6 meses (cotización por WhatsApp)
A623: 46311 | B623: Tienda | C623: Corsair Vengeance RGB DDR5 32GB (2x16) 6000 | D623: Punto Tecnológico (WhatsApp) | E623: 5960 | F623: Bs | G623: otra marca (Nox Tuf 32GB 2x16, velocidad sin dato); solo referencia; no cuenta
A624: 46311 | B624: Tienda | C624: Ryzen 5 7600 | D624: Gamer Store Cbba (WhatsApp) | E624: 2067 | F624: Bs | G624: nuevo (es el 7600X; USD 175 a 11,81; solo referencia; no cuenta)
A625: 46312 | B625: Marketplace | C625: SSD NVMe 1TB | D625: Marketplace Cochabamba (particular) | E625: 1230 | F625: Bs | G625: nuevo (antes Bs 1.730; marca sin dato) | H625: ver
A626: 46312 | B626: Marketplace | C626: SSD NVMe 1TB | D626: Marketplace Cochabamba (particular) | E626: 1500 | F626: Bs | G626: sin dato de estado ni marca (recién publicado) | H626: ver
A627: 46312 | B627: Marketplace | C627: SSD NVMe 1TB | D627: Marketplace Cochabamba (particular) | E627: 1850 | F627: Bs | G627: Kingston NV3 1TB (estado sin dato) | H627: ver
A628: 46310 | B628: Tienda | C628: SSD NVMe 2TB | D628: Shopping PC (catálogo PDF) | E628: 2726 | F628: Bs | G628: no cuenta: otro modelo (Crucial BX500 2TB es SATA, no NVMe; nuevo; lista mayorista USD 230 × 11,85 del 12/10, sin factura; 35 en stock; garantía solo de prueba; solo referencia)
A629: 46314 | B629: Marketplace | C629: Ryzen 5 5600 | D629: Marketplace Cochabamba (particular) | E629: 1800 | F629: Bs | G629: no cuenta: otro modelo (es 5600X, solo procesador, recién publicado) | H629: ver
A630: 46314 | B630: Marketplace | C630: Intel Core i5-13400 | D630: Marketplace Cochabamba (particular) | E630: 1800 | F630: Bs | G630: no cuenta: otro modelo (i5-13400F, precio fijo) | H630: ver
A631: 46314 | B631: Marketplace | C631: Intel Core i5-14400F | D631: Marketplace Cochabamba (particular) | E631: 2600 | F631: Bs | G631: no cuenta: otro modelo (i5-14400 sin F) | H631: ver
A632: 46314 | B632: Marketplace | C632: Corsair Vengeance RGB DDR5 32GB (2x16) 6000 | D632: Marketplace Cochabamba (particular) | E632: 5800 | F632: Bs | G632: Corsair Vengeance RGB 2x16 6000 MHz (estado sin dato) | H632: ver
A633: 46314 | B633: Marketplace | C633: SSD NVMe 1TB | D633: Marketplace Cochabamba (particular) | E633: 2500 | F633: Bs | G633: Lexar NM790 1TB con disipador (estado sin dato) | H633: ver
A634: 46314 | B634: Marketplace | C634: SSD NVMe 1TB | D634: Marketplace Cochabamba (particular) | E634: 2050 | F634: Bs | G634: WD Green SN3000 1TB (estado sin dato) | H634: ver
A635: 46314 | B635: Tienda | C635: Ryzen 5 7600 | D635: OverCity (WhatsApp) | E635: 2800 | F635: Bs | G635: nuevo OEM (reconfirmado 16:09)
A636: 46314 | B636: Tienda | C636: Intel Core Ultra 7 265K | D636: OverCity (WhatsApp) | E636: 4100 | F636: Bs | G636: nuevo OEM
A637: 46315 | B637: Marketplace | C637: Ryzen 7 7800X3D | D637: Marketplace Cochabamba (particular) | E637: 5190 | F637: Bs | G637: no cuenta: anuncio viejo (nuevo; publicado hace 13 semanas) | H637: ver
A638: 46315 | B638: Marketplace | C638: Ryzen 7 7800X3D | D638: Marketplace Cochabamba (particular) | E638: 5390 | F638: Bs | G638: nuevo (anuncio 'El mejor para Gaming'; disponible) | H638: ver
A639: 46315 | B639: Marketplace | C639: Intel Core Ultra 7 265K | D639: Marketplace La Paz (particular) | E639: 3950 | F639: Bs | G639: no cuenta: otra ciudad (La Paz; nuevo)
A640: 46315 | B640: Marketplace | C640: RAM DDR4 16GB (2x8) 3200 | D640: Marketplace Cochabamba (particular) | E640: 1400 | F640: Bs | G640: 2x8 = 16GB (marca y frecuencia sin dato; antes Bs 1.600; vuelve a aparecer)
A641: 46315 | B641: Marketplace | C641: Ryzen 7 7700X | D641: Marketplace Cochabamba (particular) | E641: 3000 | F641: Bs | G641: no cuenta: anuncio viejo (~7 semanas; nuevo (el anuncio dice "nuevo; se hacen pruebas si desconfía"; antes Bs 3.200)) | H641: ver
A642: 46315 | B642: Marketplace | C642: Ryzen 7 7700X | D642: Marketplace Cochabamba (particular) | E642: 4000 | F642: Bs | G642: sellado | H642: ver
A643: 46315 | B643: Marketplace | C643: Ryzen 7 7700X | D643: Marketplace La Paz (particular o tienda sin confirmar) | E643: 2800 | F643: Bs | G643: no cuenta: otra ciudad (La Paz; nuevo OEM) | H643: ver
A644: 46315 | B644: Marketplace | C644: Ryzen 7 7700X | D644: Marketplace La Paz (particular o tienda sin confirmar) | E644: 3450 | F644: Bs | G644: no cuenta: otra ciudad (La Paz; nuevo sellado) | H644: ver
A645: 46315 | B645: Tienda | C645: Ryzen 7 7700X | D645: Cyrex Store (web) | E645: 3667 | F645: Bs | G645: nuevo BOX sellado (sin cooler) | H645: ver
A646: 46316 | B646: Tienda | C646: Ryzen 7 7700X | D646: Geek Store Bolivia (WhatsApp) | E646: 3480 | F646: Bs | G646: nuevo sellado (caja)
A647: 46316 | B647: Marketplace | C647: Intel Core i5-12400F | D647: Marketplace Cochabamba (particular) | E647: 2350 | F647: Bs | G647: OEM (anuncio "Procesador CPU i5 12400f OEM"; estado sin dato)
A648: 46316 | B648: Marketplace | C648: Corsair Vengeance RGB DDR5 32GB (2x16) 6000 | D648: Marketplace Cochabamba (particular) | E648: 6200 | F648: Bs | G648: Corsair Vengeance RGB RS 2x16 6000 MHz ("última unidad"; estado sin dato)
A649: 46316 | B649: Marketplace | C649: Ryzen 7 7800X3D | D649: Marketplace Cochabamba (tienda sin confirmar) | E649: 4860 | F649: Bs | G649: nuevo (anuncio multi-modelo "9800X3D, 7800X3D, 8700G"; precio desde)
A650: 46316 | B650: Marketplace | C650: SSD NVMe 1TB | D650: Marketplace Cochabamba (particular) | E650: 1700 | F650: Bs | G650: Kingston NV2 NVMe 1TB (estado sin dato; recién publicado)
A651: 46316 | B651: Marketplace | C651: SSD NVMe 1TB | D651: Marketplace Cochabamba (particular) | E651: 3050 | F651: Bs | G651: Samsung 9100 PRO 1TB PCIe 5.0 (gama alta; estado sin dato)
A652: 46316 | B652: Tienda | C652: Ryzen 7 7800X3D | D652: ADN Gamer Store (WhatsApp) | E652: 6193 | F652: Bs | G652: nuevo (estado y garantía sin confirmar; se preguntó)
A653: 46316 | B653: Tienda | C653: Ryzen 5 7600 | D653: ADN Gamer Store (WhatsApp) | E653: 2918 | F653: Bs | G653: nuevo (es el 7600X, no el 7600; USD 245 × 11,91; solo referencia; no cuenta)
A654: 46317 | B654: Marketplace | C654: Ryzen 7 7700X | D654: Marketplace Cochabamba (particular) | E654: 3100 | F654: Bs | G654: estado sin dato (antes Bs 3.500 tachado; puede ser el mismo anuncio de Bs 3.000 de ayer con otro precio) | H654: ver
A655: 46317 | B655: Marketplace | C655: RAM DDR4 16GB (2x8) 3200 | D655: Marketplace Cochabamba (particular) | E655: 600 | F655: Bs | G655: estado sin dato (2x8 16GB; recién publicado) | H655: ver
A656: 46317 | B656: Marketplace | C656: RAM DDR4 16GB (2x8) 3200 | D656: Marketplace Cochabamba (particular) | E656: 540 | F656: Bs | G656: estado sin dato (Kingston Fury Beast RGB 16GB 3200; no queda claro si es 2x8 o un módulo) | H656: ver
A657: 46317 | B657: Marketplace | C657: SSD NVMe 1TB | D657: Marketplace Cochabamba (particular) | E657: 2050 | F657: Bs | G657: estado sin dato (WD Green SN3000 1TB) | H657: ver
A658: 46317 | B658: Marketplace | C658: SSD NVMe 1TB | D658: Marketplace Cochabamba (particular) | E658: 2060 | F658: Bs | G658: estado sin dato (WD Green SN3000 1TB) | H658: ver
A659: 46317 | B659: Tienda | C659: Ryzen 7 7800X3D | D659: ADN Gamer Store (WhatsApp) | E659: 6162 | F659: Bs | G659: nuevo en caja (box); garantía sin dato (se preguntó)
A660: 46317 | B660: Tienda | C660: Intel Core Ultra 7 265K | D660: TechMax Computers Cbba (WhatsApp) | E660: 4300 | F660: Bs | G660: no cuenta: modelo sin confirmar (dijo 'Core Ultra 7'; se preguntó si es el 265K); sin garantía, traído de EEUU; estado 'perfecto estado'
A661: 46318 | B661: Tienda | C661: Ryzen 5 5600 | D661: Punto Tecnológico · Supermall (web, vista en Google 23/10) | E661: 1710 | F661: Bs | G661: no cuenta: agotado (referencia web; ya anotada el 12/10, la web sigue mostrando el mismo precio) | H661: ver
A662: 46318 | B662: Tienda | C662: Ryzen 7 5700X3D | D662: Facebook grupo TEAM PC's BOLIVIA (web, vista en Google 23/10) | E662: 3800 | F662: Bs | G662: no cuenta: referencia vieja (comentario "de 3.800 Bs arriba" en el grupo TEAM PC's BOLIVIA; nuevo; sin ciudad ni anuncio)
A663: 46318 | B663: Tienda | C663: Ryzen 5 7500F | D663: Facebook grupo PC GAMERS BOLIVIA (web, vista en Google 23/10) | E663: 2050 | F663: Bs | G663: no cuenta: referencia vieja (2 unidades nuevas "recién llegadas" en el grupo PC GAMERS BOLIVIA; sin ciudad)
A664: 46318 | B664: Marketplace | C664: RAM DDR4 16GB (2x8) 3200 | D664: Marketplace Cochabamba (particular) | E664: 1600 | F664: Bs | G664: sin dato de estado (Corsair Vengeance Pro 2x8GB 3200 MHz) | H664: ver
A665: 46318 | B665: Marketplace | C665: RAM DDR4 16GB (2x8) 3200 | D665: Marketplace Cochabamba (particular) | E665: 1300 | F665: Bs | G665: no cuenta: velocidad sin dato (anuncio "Ram 2 x 8 = 16Gb"; estado sin dato; tachado Bs 1.600) | H665: ver
A666: 46318 | B666: Marketplace | C666: SSD NVMe 2TB | D666: Marketplace Cochabamba (particular) | E666: 3350 | F666: Bs | G666: no cuenta: tipo sin confirmar (anuncio "Sandisk SSD 2 TB recién llegadas"; tachado Bs 3.550; no dice si es NVMe o SATA) | H666: ver
A667: 46318 | B667: Tienda | C667: Ryzen 7 7700X | D667: Cyrex Store (WhatsApp) | E667: 3673.5 | F667: Bs | G667: nuevo BOX (según foto de su chat; solo queda 1 unidad)
A668: 46318 | B668: Tienda | C668: Ryzen 5 7600 | D668: Nerd Tecnologias (WhatsApp) | E668: 2700 | F668: Bs | G668: no cuenta: precio de segunda mano (lo consultó a un colega); estado y garantía sin confirmar
A669: 46318 | B669: Tienda | C669: SSD NVMe 1TB | D669: Nerd Tecnologias (WhatsApp) | E669: 1600 | F669: Bs | G669: no cuenta: precio de segunda mano (colega); marca y tipo sin confirmar ("M2 de 1 tera")
A670: 46318 | B670: Tienda | C670: Intel Core Ultra 7 265K | D670: TechMax Computers Cbba (WhatsApp) | E670: 4300 | F670: Bs | G670: no cuenta: es el Core Ultra 7 270K (no el 265K); sin garantía, traído de EEUU
A671: 46321 | B671: Marketplace | C671: Ryzen 7 7800X3D | D671: Marketplace Cochabamba (particular) | E671: 4800 | F671: Bs | G671: nuevo sellado (anuncio "AMD Ryzen 7 7800X3D (Sellado)"; el vendedor dijo el 13/10 que acepta ofertas, no se oferta)
A672: 46321 | B672: Marketplace | C672: SSD NVMe 1TB | D672: Marketplace Cochabamba (particular) | E672: 1850 | F672: Bs | G672: Kingston NV3 NVMe 1TB 6000MB/s (estado sin dato)
A673: 46321 | B673: Tienda | C673: SSD NVMe 1TB | D673: Punto Tecnológico (WhatsApp) | E673: 2000 | F673: Bs | G673: nuevo, NVMe (modelo SN3000), garantía 6 meses (confirmado 28/10)
A674: 46321 | B674: Tienda | C674: Ryzen 7 9700X | D674: Punto Tecnológico (WhatsApp) | E674: 3680 | F674: Bs | G674: no cuenta: no es producto de vigilar; OEM
A675: 46323 | B675: Marketplace | C675: Ryzen 7 7700X | D675: Marketplace Cochabamba (particular) | E675: 4000 | F675: Bs | G675: nuevo sellado ("Ryzen 7 7700x Sellado"); Cochabamba
A676: 46323 | B676: Marketplace | C676: SSD NVMe 1TB | D676: Marketplace Cochabamba (particular) | E676: 1700 | F676: Bs | G676: Kingston NV2 NVMe PCIe 4.0 1TB (estado sin dato); Cochabamba
A677: 46323 | B677: Marketplace | C677: SSD NVMe 1TB | D677: Marketplace Cochabamba (particular) | E677: 1100 | F677: Bs | G677: "Disco duro m2 NVMe 1 tb" marca y estado sin dato; Cochabamba
A678: 46323 | B678: Marketplace | C678: SSD NVMe 1TB | D678: Marketplace Cochabamba (particular) | E678: 1675 | F678: Bs | G678: Kingston NV2 NVMe 1TB (estado sin dato; "SSD NV2 de 1TB"); Cochabamba
A679: 46325 | B679: Marketplace | C679: Ryzen 7 7800X3D | D679: Marketplace Cochabamba (particular) | E679: 5190 | F679: Bs | G679: nuevo/sin dato | H679: ver
A680: 46325 | B680: Marketplace | C680: Ryzen 7 7800X3D | D680: Marketplace Cochabamba (particular) | E680: 4860 | F680: Bs | G680: no cuenta: multi-modelo a cotizar (9800X3D, 7800X3D, 8700G) | H680: ver
A681: 46325 | B681: Marketplace | C681: Ryzen 7 7700X | D681: Marketplace Cochabamba (particular) | E681: 3000 | F681: Bs | G681: estado sin dato | H681: ver
A682: 46325 | B682: Marketplace | C682: Corsair Vengeance RGB DDR5 32GB (2x16) 6000 | D682: Marketplace Cochabamba (particular) | E682: 6200 | F682: Bs | G682: sin dato (dice 'última unidad'; Vengeance RGB RS 32GB 2x16 DDR5 6000) | H682: ver
...
